Workbook

Sheet Sheet1
A1: csku | B1: cnombre | C1: cmarca | D1: cdescripcion | E1: cespecificaciones | F1: cimagen | G1: bestatus | H1: tcreate_at | I1: tupdate_at
A2: 00-0614-00-8 | B2: Cafetera Koblenz CKM-1350 en Color Negro con Acero Inoxidable Prepara Café Espresso Capiccino y Late 1350 Watts | C2: KOBLENZ | D2: Cafetera Koblenz CKM-1350 en Color Negro con Acero Inoxidable Prepara Café Espresso Capiccino y Late 1350 Watts | G2: t | H2: 46085.479 | I2: 46085.479
A3: 00-1522-00-2 | B3: Regulador Koblenz RI-20 1900VA / 1400W Entrada 120V Salida 108 - 132V 1 Salida | C3: KOBLENZ | D3: Regulador Koblenz RI-20 1900VA / 1400W Entrada 120V Salida 108 - 132V 1 Salida | E3: [{'grupo': 'Características Generales:', 'caracteristicas': [{'texto': 'Marca:', 'valor': 'Koblenz'}, {'texto': 'Artículo:', 'valor': 'Regulador'}, {'texto': 'Modelo:', 'valor': 'RI-20 C'}, {'texto': 'Color:', 'valor': 'Negro'}, {'texto': 'Capacidad:', 'valor': '1900 VA / 1400 W'}, {'texto': 'Voltaje de entrada:', 'valor': '120 VCA (operación 90–145 VCA)'}, {'texto': 'Voltaje de salida:', 'valor': '108–132 VCA'}, {'texto': 'Frecuencia:', 'valor': '60 Hz'}, {'texto': 'Salidas:', 'valor': '1 contacto aterrizado y regulado'}, {'texto': 'Protección:', 'valor': 'Autodesconexión arriba de 150 VCA y debajo de 60 VCA, disyuntor térmico 25 A'}, {'texto': 'Indicadores:', 'valor': '2 LEDs (Encendido y Desconexión automática)'}, {'texto': 'Dimensiones sin empaque:', 'valor': '14 × 12 × 19 cm'}, {'texto': 'Peso sin empaque:', 'valor': '3.2 kg'}, {'texto': 'Dimensiones con empaque:', 'valor': '19 × 16 × 22 cm'}, {'texto': 'Peso con empaque:', 'valor': '3.5 kg'}, {'texto': 'Garantía:', 'valor': '5 años'}]}] | F3: ['https://contenidos.exel.com.mx/ImagenesProductos/KB/KBCREUAB042_zoom.png', 'https://contenidos.exel.com.mx/ImagenesProductos/KB/KBCREUAB042_2_zoom.png'] | G3: t | H3: 46085.479 | I3: 46085.479
A4: 00-1560-2 | B4: Regulador Koblenz ER-2550 2500VA/2000W 6 Contactos | C4: KOBLENZ | D4: Protegen la vida de sus aparatos electrónicos y son ideales para el respaldo de equipos de cómputo y oficina. Supresor de picos integrado y fusible de extra protección. Protección de línea telefónica contra descargas atmosféricas. | E4: [{'grupo': 'Características Generales:', 'caracteristicas': [{'texto': 'Marca:', 'valor': 'Koblenz'}, {'texto': 'Artículo:', 'valor': 'Regulador'}, {'texto': 'Modelo:', 'valor': 'ER-2550'}, {'texto': 'Salida:', 'valor': 'Tensión nominal 120V~ ±10% | Sobrecarga 120% durante 1 Hora Máximo'}, {'texto': 'Entrada:', 'valor': 'Capacidad 2,500 VA / 2,000 W | Tensión nominal 120 V | Rango de regulación 95 - 145 V'}, {'texto': 'Sistema:', 'valor': 'Monofásico con tierra física'}, {'texto': 'Protecciones:', 'valor': 'Fusible de 20 A para sobrecargas y/o corto circuito'}, {'texto': 'Contactos:', 'valor': '6, (6) NEMA5-15R'}, {'texto': 'Interruptor:', 'valor': 'Encendido/apagado de uso rudo'}, {'texto': 'Dimensiones:', 'valor': '19.5 cm x 11 cm x 11 cm'}]}] | F4: ['https://contenidos.exel.com.mx/ImagenesProductos/KBCREUAB002_zoom.jpg', 'https://contenidos.exel.com.mx/ImagenesProductos/KBCREUAB002_2_zoom.jpg'] | G4: t | H4: 46085.479 | I4: 46085.479
A5: 00-1588-3 | B5: Regulador Koblenz ER-2250 2250VA/1000W 8 Contactos 1LED Garantía 5 Años | C5: KOBLENZ | D5: Regulador Koblenz ER-2250 2250VA/1000W 8 Contactos 1LED Garantía 5 Años | E5: [{'grupo': 'Características Generales:', 'caracteristicas': [{'texto': 'Marca:', 'valor': 'Koblenz'}, {'texto': 'Artículo:', 'valor': 'Regulador'}, {'texto': 'Modelo:', 'valor': 'ER-2250'}, {'texto': 'Tensión nominal(Salida):', 'valor': '120 V~ ±10%'}, {'texto': 'Sobrecarga:', 'valor': '120% durante 1 Hr máximo 200% durante 20 seg máximo'}, {'texto': 'Supresor de picos:', 'valor': '134 Joules'}, {'texto': 'Capacidad(entrada):', 'valor': '2250 VA / 1 000 W'}, {'texto': 'Tensión nominal(entrada):', 'valor': '120 V'}, {'texto': 'Rango de regulación:', 'valor': '95 - 145 V'}, {'texto': 'Corriente máxima:', 'valor': ' 8.3 A'}, {'texto': 'Frecuencia:', 'valor': '60 Hz ±3%'}, {'texto': 'Sistema:', 'valor': 'Monofásico con tierra física'}, {'texto': 'Protecciones:', 'valor': 'Disyuntor térmico'}, {'texto': 'Contactos:', 'valor': '(8) NEMA5-15R aterrizados regulados'}, {'texto': 'Indicadores visuales:', 'valor': '1 LED (Azul: encendido / LED flasheando: desconexión)'}, {'texto': 'Dimensiones:', 'valor': '19.4 cm x 11 cm x 10 cm sin caja | 22.5 cm x 11.5 cm x 10.6 cm con caja'}, {'texto': 'Peso:', 'valor': '1.62 Kg | 1.72 Kg'}]}] | F5: ['https://contenidos.exel.com.mx/ImagenesProductos/KBCREUAB025_zoom.jpg', 'https://contenidos.exel.com.mx/ImagenesProductos/KBCREUAB025_2_zoom.jpg'] | G5: t | H5: 46085.479 | I5: 46085.479
A6: 00-1596-00-6 | B6: Regulador Koblenz RI-2002 2000VA/1500W 1 Contacto | C6: KOBLENZ | D6: Regulador Koblenz RI-2002 2000VA/1500W 1 Contacto | E6: [{'grupo': 'Características Generales:', 'caracteristicas': [{'texto': 'Marca:', 'valor': 'Koblenz'}, {'texto': 'Artículo:', 'valor': 'Regulador '}, {'texto': 'Modelo:', 'valor': 'RI-2002'}, {'texto': 'Capacidad:', 'valor': '2000VA/1500W'}, {'texto': 'Contactos:', 'valor': 'aterrizados regulados (1) '}, {'texto': 'Uso:', 'valor': 'Refrigeradores 24-28 pies cúbicos, refresqueros, vitrinas, lavadoras, secadoras, microondas'}, {'texto': 'Dimensiones:', 'valor': '22 cm x 19 cm x 16 cm'}, {'texto': 'Peso:', 'valor': '4 kg'}]}] | F6: ['https://contenidos.exel.com.mx/ImagenesProductos/KBCREUAB029_zoom.jpg'] | G6: t | H6: 46085.479 | I6: 46085.479
A7: 00-1599-00-0 | B7: Regulador Koblenz RS-1410 1410VA/700W Switch 8 Contactos | C7: KOBLENZ | D7: Regulador Koblenz RS-1410 1410VA/700W Switch 8 Contactos | E7: [{'grupo': 'Características Generales:', 'caracteristicas': [{'texto': 'Marca:', 'valor': 'Koblenz'}, {'texto': 'Artículo:', 'valor': 'Regulador '}, {'texto': 'Modelo:', 'valor': 'RS-1410'}, {'texto': 'Capacidad:', 'valor': '1410 VA / 700 W'}, {'texto': 'Contactos:', 'valor': '8 contactos regulados aterrizados'}, {'texto': 'Desconexión:', 'valor': 'en alto voltaje '}, {'texto': 'Uso:', 'valor': 'Ideal para Hogar u Oficina'}, {'texto': 'Diseño:', 'valor': 'Moderno diseño con contactos en la parte superior y gabinete de plástico.'}, {'texto': 'Interruptor:', 'valor': 'de encendido/apagado de uso rudo y switch térmico protector. '}, {'texto': 'Regulación:', 'valor': '3 Pasos'}, {'texto': 'Switch:', 'valor': '8A'}, {'texto': 'Rango de tensión de salida: ', 'valor': '108 - 132 V~'}, {'texto': 'Luz:', 'valor': "2 LED's (encendido y regulando)"}, {'texto': ' Longitud Cable: ', 'valor': '1m'}, {'texto': 'Garantía:', 'valor': '2 años'}, {'texto': 'Dimensiones:', 'valor': '17.7 cm x 11.6 cm x 9.8 cm'}, {'texto': 'Peso:', 'valor': '1.214 kg'}]}] | F7: ['https://contenidos.exel.com.mx/ImagenesProductos/KBCREUAB030_zoom.jpg'] | G7: t | H7: 46085.479 | I7: 46085.479
A8: 00-3121-00-1 | B8: Horno Freidora Koblenz HFKM-1400 de Acero Inoxidable 1400 Watts 4 Programas de Cocción | C8: KOBLENZ | D8: Horno Freidora Koblenz HFKM-1400 de Acero Inoxidable 1400 Watts 4 Programas de Cocción | G8: t | H8: 46085.479 | I8: 46085.479
A9: 00-4196-2 | B9: UPS Koblenz 20012 USB/R Línea Pro 2KVA/1200W 8 Contactos 6 LEDS | C9: KOBLENZ | D9: Excelente microprocesador que garantiza una excelente fiabilidad. Ideal para la protección de equipos de escritorio. Auto reinicio mientras se recupera la corriente. | E9: [{'grupo': 'Características Generales:', 'caracteristicas': [{'texto': 'Marca:', 'valor': 'Koblenz'}, {'texto': 'Artículo:', 'valor': 'UPS'}, {'texto': 'Modelo:', 'valor': '20012 USB/R'}, {'texto': 'Tipo:', 'valor': 'Interactivo con regulador de voltaje integrado'}, {'texto': 'Capacidad:', 'valor': 'Potencia 2000 VA/ 1200 W'}, {'texto': 'Fase Monofásica:', 'valor': '120V'}, {'texto': 'Topología:', 'valor': 'onda cuasisenoidal'}, {'texto': 'Arranque:', 'valor': 'en frío Soportado'}, {'texto': 'Tensión de salida nominal:', 'valor': '120Vca ± 10%'}, {'texto': 'Frecuencia de salida:', 'valor': '50/60 Hz'}, {'texto': 'Conexiones de salida:', 'valor': '(6) NEMA 5-15R con protección de batería y (2) NEMA 5-15R con supresión de picos'}, {'texto': 'Capacidad de sobrecarga:', 'valor': '(con tensión de línea) 25%'}, {'texto': 'Voltaje de Entrada:', 'valor': '120 V'}, {'texto': 'Rango de Voltaje:', 'valor': '89 - 145 Vca'}, {'texto': 'Frecuencia de Entrada:', 'valor': '60 Hz ± 5%'}, {'texto': 'Tipo de Clavija:', 'valor': 'NEMA 5-15P'}, {'texto': 'Longitud del Cable:', 'valor': '1.8m'}, {'texto': 'Tipo de Batería:', 'valor': 'VRLA batería sellada de plomo ácido libre de mantenimiento a prueba de filtración'}, {'texto': 'Baterías Pre-Instaladas:', 'valor': '(2) 12V 9Ah'}, {'texto': 'Panel Control LED:', 'valor': 'odo AC - (En línea) modo batería, batería baja, sobrecarga, reemplazo de batería'}, {'texto': 'Supresión de Pico:', 'valor': '316 Joules'}, {'texto': 'Dimensiones:', 'valor': '39.7 cm x 20.5 cm x 14.6 cm'}, {'texto': 'Peso:', 'valor': '11.5 kg'}]}] | F9: ['https://contenidos.exel.com.mx/ImagenesProductos/KBCREUAB024_zoom.jpg'] | G9: t | H9: 46085.479 | I9: 46085.479
A10: 00-4206-9 | B10: Regulador Koblenz 7016 NoBreak USB/R 700VA/360W Respaldo 25 Minutos 6 Contactos Garantía 3 Años | C10: KOBLENZ | D10: Construido con cargador inteligente que reduce hasta 50% el tiempo de carga. Regulador de voltaje integrado (altos y bajos) que permite la estabilización del voltaje, 6 contactos NEMA 5-15R. | E10: [{'grupo': 'Características Generales:', 'caracteristicas': [{'texto': 'Marca:', 'valor': 'Koblenz'}, {'texto': 'Artículo:', 'valor': 'Regulador/UPS'}, {'texto': 'Modelo:', 'valor': '7016 USB/R'}, {'texto': 'Salida:', 'valor': 'Capacidad potencia 700 VA / 360 W | Tensión de salida nominal 120V distorsión ±10%'}, {'texto': 'Fase:', 'valor': 'Monofásica 120 V'}, {'texto': 'Topología:', 'valor': 'Linea interactiva'}, {'texto': 'Frecuencia de salida en modo batería:', 'valor': '60 Hz ±1 Hz'}, {'texto': 'Tipo de forma de onda:', 'valor': 'Senoidal simulada'}, {'texto': 'Conexiones de salida:', 'valor': '(4) NEMA 5-15R con protección de batería OPCIÓN A: (3) NEMA 5-15R con protección de batería | (2) NEMA 5-15R sin protección de batería OPCIÓN A: (3) NEMA 5-15R sin protección de batería'}, {'texto': 'Entrada:', 'valor': 'Voltaje 120 V | Rango de voltaje 90 - 145 Vca | Frecuencia de entrada 60 Hz / 50 Hz'}, {'texto': 'Tipo de enchufe:', 'valor': 'NEMA 5-15P'}, {'texto': 'Longitud del cable:', 'valor': '1.5 metros (fijo) integrado al equipo'}, {'texto': 'Tipo de batería:', 'valor': 'Batería sellada de plomo ácido libre de mantenimiento a prueba de filtración'}, {'texto': 'Baterías pre-instaladas:', 'valor': '(1) 12V 7Ah'}, {'texto': 'Tiempo recarga:', 'valor': '4 horas al 90%'}, {'texto': 'Puerto de interfaz:', 'valor': 'USB'}, {'texto': 'Panel control:', 'valor': '(3) LED indicadores - en línea, en batería, falla'}, {'texto': 'Protección:', 'valor': 'Supresión de picos - 365 Joules y protector térmico contra sobrecargas | RJ-11 (2)'}, {'texto': 'Dimensiones:', 'valor': '28.9 cm 14.2 cm x 9.7 cm'}]}] | F10: ['https://contenidos.exel.com.mx/ImagenesProductos/KBCREUAB005_zoom.jpg', 'https://contenidos.exel.com.mx/ImagenesProductos/KBCREUAB005_2_zoom.jpg'] | G10: t | H10: 46085.479 | I10: 46085.479
A11: 00-4226-7 | B11: UPS Koblenz 15012 USB/RN Línea Pro 1.5 KVA/900W 8 Contactos 6 LEDS | C11: KOBLENZ | D11: Cargador de baterías inteligente integrado que reduce hasta en un 50% el tiempo de carga. Excelente microprocesador que garantiza una excelente fiabilidad. Ideal para la protección de equipos de escritorio | G11: t | H11: 46085.479 | I11: 46085.479
A12: 00-4231-7 | B12: UPS Koblenz One Line Doble Conversión 30015 OL USB/R 3KVA/2700W 2 y 1 Contactos Senoidal Pura | C12: KOBLENZ | D12: UPS on line de doble conversión ideal para el respaldo de aplicaciones críticas de voz, datos, redes, servidores, sistemas de seguridad y sistemas de fabricación. Su tiempo de transferencia cero garantiza el funcionamiento continuo durante cortes de corriente, fluctuaciones de voltaje y sobretensiones. Salida de onda senoidal pura que garantiza la compatibilidad con cualquier equipo. Función ECO que permite la disminución de la producción de calor y el ahorro en costos de energía. | G12: t | H12: 46085.479 | I12: 46085.479
A13: 00-4233-3 | B13: Regulador Koblenz 10017 NoBreak USB/R 1000VA/500 Respaldo 60 Minutos 8 Contactos Garantía 3 Años | C13: KOBLENZ | D13: Excelente microprocesador de control que garantiza una alta fiabilidad. Regulador de voltaje de 4 pasos (2 Boost, 1 Buck, 1 Neutro) que permite la estabilización del voltaje | E13: [{'grupo': 'Características Generales:', 'caracteristicas': [{'texto': 'Marca:', 'valor': 'Koblenz'}, {'texto': 'Artículo:', 'valor': 'Regulador/UPS'}, {'texto': 'Modelo:', 'valor': '10017 USB/R'}, {'texto': 'Capacidad potencia:', 'valor': '1,000 VA/ 500 W'}, {'texto': 'Fase:', 'valor': 'Monofásica 120 V'}, {'texto': 'Topología:', 'valor': 'Línea interactiva onda cuasisenoidal'}, {'texto': 'Salida:', 'valor': 'Tensión de salida nominal 120V ± 10% | Frecuencia de salida en modo batería 60 Hz ± 1 Hz'}, {'texto': 'Tipo de forma de onda:', 'valor': 'Cuasisenoidal'}, {'texto': 'Conexiones de salida:', 'valor': '(4) NEMA 5-15R con protección de batería | (4) NEMA 5-15R con supresión de picos'}, {'texto': 'Entrada:', 'valor': 'Voltaje 120 V | Rango de voltaje 85-145 Vca | Frecuencia de entrada 60 Hz ± 5Hz'}, {'texto': 'Tipo de clavija:', 'valor': 'NEMA 5-15P'}, {'texto': 'Longitud del cable:', 'valor': '1.8 metros'}, {'texto': 'Tipo de batería:', 'valor': 'VRLA batería sellada de plomo ácido libre de mantenimiento a prueba de filtración'}, {'texto': 'Baterías pre-instaladas:', 'valor': '12V 9Ah'}, {'texto': 'Tiempo recarga:', 'valor': '4-8 horas al 90%'}, {'texto': 'Puerto de interfaz:', 'valor': 'USB'}, {'texto': 'Panel de control:', 'valor': 'LED: modo AC (en línea), modo batería, batería baja, sobrecarga, reemplazo batería'}, {'texto': 'Protección:', 'valor': 'Supresión de picos - 450 Joules | RJ11'}, {'texto': 'Ambiente operativo:', 'valor': '0-90% RH. 0 - 40 ºC sin condensación'}]}] | F13: ['https://contenidos.exel.com.mx/ImagenesProductos/KBCREUAB007_zoom.jpg'] | G13: t | H13: 46085.479 | I13: 46085.479
A14: 00-4235-00-8 | B14: UPS Koblenz One Line Doble Conversión 60019 OL 2 P 6KVA/6000W Bifásico Senoidal Pura | C14: KOBLENZ | D14: UPS on line de doble conversión ideal para el respaldo de aplicaciones críticas de voz, datos, redes, servidores, sistemas de seguridad y sistemas de fabricación. Tecnología de DSP que garantiza un alto rendimiento.Factor de potencia 1. Comunicación SNMP / USB / RS - 232. | G14: t | H14: 46085.479 | I14: 46085.479
A15: 00-4237-00-4 | B15: UPS Koblenz No Break Interactivo 15007 USB/R Onda Cuasisenoidal 1500VA/900W 7 Contactos | C15: KOBLENZ | D15: UPS línea Interactiva con regulador de voltaje integrado, ideal para la protección de equipos de escritorio. Protección para teléfono, fax modem RJ-11 y cable coaxial RG6. Protección contra sobre carga a través de un indicador visual y alarma audible. Regulador de voltaje integrado (altos y bajos) que permite la estabilización del voltaje. | G15: t | H15: 46085.479 | I15: 46085.479
A16: 00-4239-00-0 | B16: UPS Koblenz One Line Doble Conversión 20015 OL USB/R 2KVA/1600W 8 Contactos Senoidal Pura | C16: KOBLENZ | D16: UPS on line de doble conversión ideal para el respaldo de aplicaciones críticas de voz, datos, redes, servidores, sistemas de seguridad y sistemas de fabricación. Su tiempo de transferencia cero garantiza el funcionamiento continuo durante cortes de corriente, fluctuaciones de voltaje y sobretensiones. Salida de onda senoidal pura que garantiza la compatibilidad con cualquier equipo. Función ECO que permite la disminución de la producción de calor y el ahorro en costos de energía. | G16: t | H16: 46085.479 | I16: 46085.479
A17: 00-4240-00-8 | B17: UPS Koblenz Online Doble Conversión 10KVA/10000W Ideal para Respaldo de Aplicaciones Críticas | C17: KOBLENZ | D17: UPS Koblenz Online Doble Conversión 10KVA/10000W Ideal para Respaldo de Aplicaciones Críticas | G17: t | H17: 46085.479 | I17: 46085.479
A18: 00-4241-00-6 | B18: Regulador Koblenz 5216 R NoBreak 520VA/240W 6 Contactos | C18: KOBLENZ | D18: Protección para teléfono y fax modem RJ-1, 6 contactos NEMA 5-15R. Excelente microprocesador de control que garantiza una alta fiabilidad | E18: [{'grupo': 'Características Generales:', 'caracteristicas': [{'texto': 'Marca:', 'valor': 'Koblenz'}, {'texto': 'Artículo:', 'valor': 'Regulador/UPS'}, {'texto': 'Modelo:', 'valor': '5216 R'}, {'texto': 'Salida:', 'valor': 'Capacidad potencia 520 VA / 240 W | Tensión de salida nominal 120V distorsión ±10%'}, {'texto': 'Fase:', 'valor': 'Monofásica 120V'}, {'texto': 'Topología:', 'valor': 'Linea interactiva'}, {'texto': 'Frecuencia de salida en modo batería:', 'valor': '60 Hz ±1 Hz'}, {'texto': 'Conexiones de salida:', 'valor': '(3) NEMA 5-15R con protección de batería | (3) NEMA 5-15R sin protección de batería'}, {'texto': 'Tipo de forma de onda:', 'valor': 'Senoidal simulada'}, {'texto': 'Entrada:', 'valor': 'Voltaje 120V | Rango de voltaje 90 - 145 Vca | Frecuencia de entrada 60Hz '}, {'texto': 'Tipo de enchufe:', 'valor': 'NEMA 5-15P'}, {'texto': 'Longitud del cable:', 'valor': '1.5 metros'}, {'texto': 'Tipo de batería:', 'valor': 'Batería sellada de plomo ácido libre de mantenimiento a prueba de filtración'}, {'texto': 'Baterías pre-instaladas:', 'valor': '(1) 12V 4.5Ah'}, {'texto': 'Tiempo recarga:', 'valor': '4 horas al 90%'}, {'texto': 'Puerto de interfaz:', 'valor': 'USB'}, {'texto': 'Panel control:', 'valor': 'Pantalla LCD'}, {'texto': 'Protección:', 'valor': 'Supresión de picos 268 Joules | RJ-11'}, {'texto': 'Dimensiones:', 'valor': '29.1 cm x 13.9 cm x 10 cm'}]}] | F18: ['https://contenidos.exel.com.mx/ImagenesProductos/KBCREUAB004_zoom.jpg'] | G18: t | H18: 46085.479 | I18: 46085.479
A19: 00-4253-00-1 | B19: UPS Koblenz Online Doble Conversión 20KVA/18000W Ideal para Respaldo para Aplicaciones Críticas | C19: KOBLENZ | D19: UPS Koblenz Online Doble Conversión 20KVA/18000W Ideal para Respaldo para Aplicaciones Críticas | G19: t | H19: 46085.479 | I19: 46085.479
A20: 00-4257-00-2 | B20: UPS Koblenz 7522 USB/R 750VA/420W 10 Contactos 65 Minutos de Respaldo con una AIO | C20: KOBLENZ | D20: UPS Koblenz 7522 USB/R 750VA/420W 10 Contactos 65 Minutos de Respaldo con una AIO | G20: t | H20: 46085.479 | I20: 46085.479
A21: 00-4258-00-0 | B21: UPS Koblenz 9022 USB/R 900VA/450W 10 Contactos 76 Minutos de Respaldo con una AIO | C21: KOBLENZ | D21: UPS Koblenz 9022 USB/R 900VA/450W 10 Contactos 76 Minutos de Respaldo con una AIO | E21: [{'grupo': 'Características Generales:', 'caracteristicas': [{'texto': 'Marca:', 'valor': 'Koblenz'}, {'texto': 'Artículo:', 'valor': 'UPS/No Break'}, {'texto': 'Modelo:', 'valor': '9022-USB'}, {'texto': 'Tipo:', 'valor': 'Interactivo, onda cuasisenoidal'}, {'texto': 'Capacidad:', 'valor': '900 VA / 450 W'}, {'texto': 'Contactos:', 'valor': '5 respaldados, 5 con supresión de picos'}, {'texto': 'Respaldo:', 'valor': 'Hasta 76 minutos con una AIO'}, {'texto': 'Pantalla:', 'valor': 'LCD con indicador de Voltaje de entrada y salida, nivel de carga de la batería, nivel de carga del no break'}, {'texto': 'Puertos:', 'valor': 'USB de comunicación'}, {'texto': 'Batería:', 'valor': 'fácilmente desmontable 12V / 9 Ah'}, {'texto': 'Dimensiones:', 'valor': '39.2 cm x 26 cm x 14.5 cm'}, {'texto': 'Peso:', 'valor': '4.6 kg'}]}] | F21: ['https://contenidos.exel.com.mx/ImagenesProductos/KBCREUAB027_zoom.jpg'] | G21: t | H21: 46085.479 | I21: 46085.479
A22: 00-4260-00-6 | B22: UPS Koblenz 7516 USBR 750VA/450W 6 Contactos | C22: KOBLENZ | D22: UPS Línea Interactiva con Regulador de Voltaje integrado, ideal para la protección de equipos de escritorio. Factor de potencia 0.6. Protección contra sobre carga y corto circuito. Regulador de voltaje integrado (Altos y bajos) que permite la estabilización del voltaje. Arranque en frío modo batería. Indicadores LED para modo línea, batería, sobrecarga batería baja / reemplazo. Tiempo de respaldo 75 min. | E22: [{'grupo': 'Características Generales:', 'caracteristicas': [{'texto': 'Marca:', 'valor': 'Koblenz'}, {'texto': 'Artículo:', 'valor': 'UPS'}, {'texto': 'Modelo:', 'valor': '7516 USB/R'}, {'texto': 'Capacidad potencia:', 'valor': '750VA / 450W'}, {'texto': 'Fase:', 'valor': 'Monofásica 120V'}, {'texto': 'Topología:', 'valor': 'Línea interactiva'}, {'texto': 'Tiempo de transferencia:', 'valor': 'Típico 2-6 ms, 10 ms máximo'}, {'texto': 'Tensión de salida nominal:', 'valor': '120 Vca ±5%'}, {'texto': 'Frecuencia de salida en modo batería:', 'valor': '60 Hz ±1 Hz'}, {'texto': 'Tipo de forma de onda:', 'valor': 'Senoidal simulada PWM'}, {'texto': 'Conexiones de salida:', 'valor': '(4) NEMA 5-15R con protección de batería, (2) NEMA 5-15R sin protección de batería'}, {'texto': 'Voltaje de entrada:', 'valor': '120V - 127 V'}, {'texto': 'Rango de voltaje:', 'valor': '95 - 140 Vca'}, {'texto': 'Frecuencia de entrada:', 'valor': '60 Hz'}, {'texto': 'Tipo de clavija:', 'valor': 'NEMA 5-15P'}, {'texto': 'Tipo de batería:', 'valor': 'VRLA Batería sellada de plomo ácido libre de mantenimiento a prueba de filtración'}, {'texto': 'Baterías pre-instaladas:', 'valor': '(1) 12V 9 Ah'}, {'texto': 'Tiempo de Respaldo:', 'valor': '75 min'}, {'texto': 'Tiempo recarga:', 'valor': '4 hrs al 90%'}, {'texto': 'Baterías externas adicionales:', 'valor': 'No'}, {'texto': 'Puerto de interfaz:', 'valor': 'USB'}, {'texto': 'Tarjeta SNMP:', 'valor': 'No soportado'}, {'texto': 'Panel control:', 'valor': '(4) LED indicadores: Modo línea, modo batería, sobrecarga y batería baja/reemplazar'}, {'texto': 'Alarmas audibles:', 'valor': 'Modo de batería: sonido cada 10 segundos Batería baja: sonido cada segundo Sobrecarga: doble sonido cada 0.5 segundos Reemplazo de batería: sonido cada 2 segundos Falla: sonido contínuo'}, {'texto': 'Software:', 'valor': 'View Power'}, {'texto': 'Supresión de picos:', 'valor': 'Switch termomagnetico 7 A'}, {'texto': 'Ambiente operativo:', 'valor': '0-90% RH @ 0 - 40 ºC Sin Condensación'}, {'texto': 'Formato:', 'valor': 'Torre'}, {'texto': 'Gabinete:', 'valor': 'Plástico'}, {'texto': 'Dimensiones:', 'valor': '28.9 cm x 14.2 cm x 9.7 cm'}, {'texto': 'Peso:', 'valor': '4.25 kg'}, {'texto': 'Garantía:', 'valor': '3 Años'}, {'texto': 'Garantía de batería:', 'valor': '2 Años'}, {'texto': 'Certificaciones:', 'valor': 'NOM-001-SCFI-1993, ISO 9001:2015'}]}] | F22: ['https://contenidos.exel.com.mx/ImagenesProductos/KBCREUAB032_zoom.jpg'] | G22: t | H22: 46085.479 | I22: 46085.479
A23: 00-4263-00-0 | B23: UPS Koblenz 7616 USB/R 750VA/450W 6 Contactos (4/6) con Regulador Integrado | C23: KOBLENZ | D23: UPS Línea Interactiva con Regulador de Voltaje integrado, ideal para la protección de equipos de escritorio. Regulador de voltaje integrado (Altos y bajos) que permite la estabilización del voltaje. | E23: [{'grupo': 'Características Generales:', 'caracteristicas': [{'texto': 'Marca:', 'valor': 'Koblenz '}, {'texto': 'Artículo:', 'valor': 'UPS '}, {'texto': 'Capacidad:', 'valor': '750VA/450W'}, {'texto': 'Cantidad / Tipo de Salidas:', 'valor': '4 x NEMA 5-15R (con protección de batería y supresión de sobretensión) 2 x NEMA 5-15R (sin protección de batería con supresión de sobretensión)'}, {'texto': 'Otros: ', 'valor': 'con Regulador Integrado'}, {'texto': 'Fase:', 'valor': 'Monofásica 120V'}, {'texto': 'Topología:', 'valor': 'Línea interactiva'}, {'texto': 'Tiempo de transferencia:', 'valor': 'Típico 4 ms (Típico)'}, {'texto': 'Tensión de salida nominal:', 'valor': '-18% +18% 120 Vca ±5%'}, {'texto': 'Voltaje de entrada:', 'valor': '120 Vca ±5%'}, {'texto': 'Tipo de clavija:', 'valor': 'Interconstruido con clavija NEMA 5-15P'}, {'texto': 'Tipo de batería:', 'valor': 'VRLA Batería sellada de plomo ácido libre de mantenimiento a prueba de filtración'}, {'texto': 'Baterías pre-instaladas:', 'valor': '(1) 12V 9 Ah'}, {'texto': 'Panel control:', 'valor': '(4) LED indicadores: Modo línea, modo batería, sobrecarga y batería baja/ reemplazar'}, {'texto': 'Dimensiones:', 'valor': '28.7 cm x 14.2 cm x 10 cm'}, {'texto': 'Peso:', 'valor': '4.25 kg'}]}] | F23: ['https://contenidos.exel.com.mx/ImagenesProductos/KB/KBCREUAB039_zoom.jpg'] | G23: t | H23: 46085.479 | I23: 46085.479
A24: 00-5328-00-0 | B24: Supresor Pared Koblenz SS-1100 USB 100 Joules 7 Contactos/2 Puertos USB 2.4A LED | C24: KOBLENZ | D24: Supresor Pared Koblenz SS-1100 USB 100 Joules 7 Contactos/2 Puertos USB 2.4A LED | G24: t | H24: 46085.479 | I24: 46085.479
A25: 00-5333-00-0 | B25: Supresor Koblenz SS-550 USB 550 Joules 5 Contactos Aterrizados Switch On/Off 2 Puertos USB | C25: KOBLENZ | D25: El supresor de picos Koblenz verifica la entrada de energía constantemente y cuando detecta un valor de corriente o voltaje alto los componentes especialmente diseñados dentro del supresor lo recortan o amortiguan dando a sus equipos una protección instantánea | G25: t | H25: 46085.479 | I25: 46085.479
A26: 00-5340-00-5 | B26: Supresor Koblenz SS-420-C 420 Joules 6 Contactos Aterrizados Switch On/Off | C26: KOBLENZ | D26: El supresor de picos Koblenz verifica la entrada de energía constantemente y cuando detecta un valor de corriente o voltaje alto los componentes especialmente diseñados dentro del supresor lo recortan o amortiguan dando a sus equipos una protección instantánea | E26: [{'grupo': 'Características Generales:', 'caracteristicas': [{'texto': 'Marca:', 'valor': 'Koblenz'}, {'texto': 'Artículo:', 'valor': 'Supresor'}, {'texto': 'Modelo:', 'valor': 'SS-420-C'}, {'texto': 'Salida:', 'valor': 'Contactos aterrizados - (6) NEMA 5-15R'}, {'texto': 'Entrada:', 'valor': 'Voltaje 120V | Frecuencia de entrada 60 Hz'}, {'texto': 'Tipo de enchufe:', 'valor': 'NEMA 5-15P'}, {'texto': 'Longitud de cable:', 'valor': '0.45 metros'}, {'texto': 'Capacidad del disyuntor de entrada:', 'valor': '15 A'}, {'texto': 'Protección:', 'valor': 'Clasificación de energía de sobrecarga 420 Joules '}, {'texto': 'Switch:', 'valor': 'On / Off Iluminado con reset'}, {'texto': 'Material:', 'valor': 'Plástico'}]}] | F26: ['https://contenidos.exel.com.mx/ImagenesProductos/KBCSUPAB001_zoom.jpg'] | G26: t | H26: 46085.479 | I26: 46085.479
A27: 00-5342-00-1 | B27: Supresor Koblenz SS-460-C 460 Joules 6 Contactos Aterrizados Switch On/Off | C27: KOBLENZ | D27: El supresor de picos Koblenz verifica la entrada de energía constantemente y cuando detecta un valor de corriente o voltaje alto los componentes especialmente diseñados dentro del supresor lo recortan o amortiguan dando a sus equipos una protección instantánea | E27: [{'grupo': 'Características Generales:', 'caracteristicas': [{'texto': 'Marca:', 'valor': 'Koblenz'}, {'texto': 'Artículo:', 'valor': 'Supresor '}, {'texto': 'Modelo:', 'valor': 'SS-460-C'}, {'texto': 'Salida:', 'valor': 'Contactos aterrizados - (6) NEMA 5-15R'}, {'texto': 'Entrada:', 'valor': 'Voltaje 120V | Frecuencia de entrada 60 Hz'}, {'texto': 'Tipo de enchufe:', 'valor': 'NEMA 5-15P'}, {'texto': 'Longitud de cable:', 'valor': '0.45 metros'}, {'texto': 'Capacidad del disyuntor de entrada:', 'valor': '15 A'}, {'texto': 'Protección:', 'valor': 'Clasificación de energía de sobrecarga 460 Joules'}, {'texto': 'Switch:', 'valor': 'On / Off Iluminado con reset'}, {'texto': 'Material:', 'valor': 'Plástico'}]}] | F27: ['https://contenidos.exel.com.mx/ImagenesProductos/KBCSUPAB002_zoom.jpg'] | G27: t | H27: 46085.479 | I27: 46085.479
A28: 00-5347-00-0 | B28: Supresor Picos Koblenz PV-2500 D 2500 VA/2000W 6 Contactos Desconexión Automática con Alto o Bajo Voltaje | C28: KOBLENZ | D28: Supresor Picos Koblenz PV-2500 D 2500 VA/2000W 6 Contactos Desconexión Automática con Alto o Bajo Voltaje | G28: t | H28: 46085.479 | I28: 46085.479
A29: 00-5348-00-8 | B29: Supresor Picos Koblenz SS2000 USB 2000 Joules 6 Contactos 2 Puertos USB | C29: KOBLENZ | D29: Supresor Picos Koblenz SS2000 USB 2000 Joules 6 Contactos 2 Puertos USB | E29: [{'grupo': 'Características Generales:', 'caracteristicas': [{'texto': 'Marca:', 'valor': 'Koblenz'}, {'texto': 'Artículo:', 'valor': 'Supresor de picos'}, {'texto': 'Tipo:', 'valor': 'Multicontacto con Conexión USB'}, {'texto': 'Protección:', 'valor': '2,000 Joules '}, {'texto': 'Contactos:', 'valor': '6 Contactos giratorios NEMA 5-15R'}, {'texto': 'Puertos:', 'valor': '2 Puertos USB 2.4A 5Vcc '}, {'texto': 'Ruido:', 'valor': 'Filtro de ruido de 40dB'}, {'texto': 'Potencia:', 'valor': '15A'}, {'texto': 'Dimensiones:', 'valor': '23 cm x 11.8 cm x 6.2 cm'}, {'texto': 'Peso:', 'valor': '0.327 Kg'}]}] | F29: ['https://contenidos.exel.com.mx/ImagenesProductos/KBCSUPAB004_zoom.jpg', 'https://contenidos.exel.com.mx/ImagenesProductos/KBCSUPAB004_2_zoom.jpg', 'https://contenidos.exel.com.mx/ImagenesProductos/KBCSUPAB004_3_zoom.jpg'] | G29: t | H29: 46085.479 | I29: 46085.479
A30: 00-5360-00-3 | B30: Supresor Picos Koblenz SS-1100 USBAC 7 contactos 2 puertos USB 1100J | C30: KOBLENZ | D30: Supresor Picos Koblenz SS-1100 USBAC 7 contactos 2 puertos USB 1100J | E30: [{'grupo': 'Características Generales:', 'caracteristicas': [{'texto': 'Marca:', 'valor': 'Koblenz'}, {'texto': 'Artículo:', 'valor': 'Supresor '}, {'texto': 'Modelo:', 'valor': 'SS-1100 USBAC'}, {'texto': 'Multicontacto:', 'valor': 'Supresor de picos con conexión USB C'}, {'texto': 'Filtro de ruido:', 'valor': 'Ayuda a que al encender o usar algún aparato eléctrico el uso de energía de ese aparato no interrumpa o afecte la operación de los aparatos que están conectados al supresor'}, {'texto': 'Logo:', 'valor': '"K" LED frontal indica que el aparato está funcionando y la línea está protegida'}, {'texto': 'Contactos tipo NEMA 5-15R:', 'valor': '7'}, {'texto': 'Puerto USB tipo C de 35 Watts de carga rápida:', 'valor': '1'}, {'texto': 'Potencia:', 'valor': '15A'}, {'texto': 'Otros:', 'valor': 'Sin cables, se enchufa directo a la pared | Gabinete de plástico'}, {'texto': 'Color:', 'valor': 'Blanco'}, {'texto': 'Dimensiones con empaque:', 'valor': '23x19x7cm | Peso: 270 g '}, {'texto': 'Dimensiones sin empaque:', 'valor': '15.5x9.5x5.5cm | Peso: 217 g'}]}] | F30: ['https://contenidos.exel.com.mx/ImagenesProductos/KB/KBCSUPAB007_zoom.jpg'] | G30: t | H30: 46085.479 | I30: 46085.479
A31: 00-5361-00-1 | B31: MULTICONTACTO KOBLENZ SUPRESOR DE PICOS 2000 Joules 6 contactos guratorios 1 led 1 puertos USB A | C31: KOBLENZ | D31: MULTICONTACTO KOBLENZ SUPRESOR DE PICOS 2000 Joules 6 contactos guratorios 1 led 1 puertos USB A | E31: [{'grupo': 'Características Generales:', 'caracteristicas': [{'texto': 'Marca:', 'valor': 'Koblenz'}, {'texto': 'Artículo:', 'valor': 'Multicontacto'}, {'texto': 'Altura:', 'valor': '190 mm'}, {'texto': 'Profundidad:', 'valor': '40 mm'}, {'texto': 'Peso:', 'valor': '217 g'}, {'texto': 'Ancho:', 'valor': '90 mm'}, {'texto': 'Cantidad de puertos USB:', 'valor': '2'}, {'texto': 'Periodo de garantía:', 'valor': '3 Año(s)'}, {'texto': 'EMI/RFI, filtro de ruido:', 'valor': '40 dB'}, {'texto': 'Ancho del paquete:', 'valor': '118 mm'}, {'texto': 'Peso del paquete:', 'valor': '327 g'}, {'texto': 'Altura del paquete:', 'valor': '230 mm'}, {'texto': 'Tipo de salida AC:', 'valor': 'NEMA 5-15R'}, {'texto': 'Corriente nominal de salida:', 'valor': '15 A'}, {'texto': 'Carga por USB:', 'valor': 'Sí'}, {'texto': 'Cantidad de salidas AC:', 'valor': '6 Salidas'}, {'texto': 'Índice de aumento de energía:', 'valor': '2,000 Joules'}, {'texto': 'Materiales:', 'valor': 'Plástico'}, {'texto': 'Color del producto:', 'valor': 'Gris'}]}] | F31: ['https://contenidos.exel.com.mx/ImagenesProductos/KB/KBCSUPAB008_zoom.jpg'] | G31: t | H31: 46085.479 | I31: 46085.479
A32: 00-5369-00-4 | B32: Supresor Rojo Koblenz SS-300-C 300 Joules 6 Contactos Aterrizados Switch On/Off | C32: KOBLENZ | D32: Supresor Rojo Koblenz SS-300-C 300 Joules 6 Contactos Aterrizados Switch On/Off | E32: [{'grupo': 'Características Generales:', 'caracteristicas': [{'texto': 'Marca:', 'valor': 'Koblenz'}, {'texto': 'Artículo:', 'valor': 'Supresor'}, {'texto': 'Modelo:', 'valor': 'SS-300-C'}, {'texto': 'Color:', 'valor': 'Rojo'}, {'texto': 'Contactos:', 'valor': '6 Cotactos aterrizados'}, {'texto': 'Pprotección:', 'valor': '300 Joules'}, {'texto': 'Switch:', 'valor': 'Reset iluminado de 10 Amp'}, {'texto': 'Cable:', 'valor': '45cm'}, {'texto': 'Garantía:', 'valor': '1 año'}, {'texto': 'Dimensiones sin empaque:', 'valor': '12.5cm x 9.5cm x 3.5cm | Peso: 0.280 kg'}]}] | F32: ['https://contenidos.exel.com.mx/ImagenesProductos/KB/KBCSUPAB009_zoom.jpg', 'https://contenidos.exel.com.mx/ImagenesProductos/KB/KBCSUPAB009_2_zoom.jpg', 'https://contenidos.exel.com.mx/ImagenesProductos/KB/KBCSUPAB009_3_zoom.jpg', 'https://contenidos.exel.com.mx/ImagenesProductos/KB/KBCSUPAB009_4_zoom.jpg'] | G32: t | H32: 46085.479 | I32: 46085.479
A33: 0001 | B33: REGISTRADOR LEFORT 0001 CLASICO CARTA MARMOLEADO S/INDEX | C33: LEFORT | D33: REGISTRADOR LEFORT 0001 CLASICO CARTA MARMOLEADO S/INDEX | E33: [{'grupo': 'Especificaciones Generales', 'caracteristicas': [{'texto': 'Tamaño', 'valor': 'Carta'}, {'texto': 'Color', 'valor': 'Marmoleado'}]}] | G33: t | H33: 46085.479 | I33: 46085.479
A34: 0002 | B34: Registrador Lefort 0002 Clásico Oficio Marmoleado S/Index | C34: LEFORT | D34: Registrador Lefort 0002 Clásico Oficio Marmoleado S/Index | E34: [{'grupo': 'Especificaciones Generales', 'caracteristicas': [{'texto': 'Tamaño', 'valor': 'Oficio'}, {'texto': 'Color', 'valor': 'Marmoleado'}]}] | F34: ['https://contenidos.exel.com.mx/ImagenesProductos/LF/LFPREGAB010_zoom.jpg', 'https://contenidos.exel.com.mx/ImagenesProductos/LF/LFPREGAB010_2_zoom.jpg'] | G34: t | H34: 46085.479 | I34: 46085.479
A35: 0003 | B35: REGISTRADOR LEFORT MARMOLEADO TAMAÑO ESQUELA | C35: LEFORT | D35: REGISTRADOR LEFORT MARMOLEADO TAMAÑO ESQUELA | E35: [{'grupo': 'Especificaciones Generales', 'caracteristicas': [{'texto': 'Detalle:', 'valor': 'REGISTRADOR LEFORT MARMOLEADO TAMAÑO ESQUELA'}]}] | F35: ['https://contenidos.exel.com.mx/ImagenesProductos/LF/LFPREGAB011_zoom.jpg'] | G35: t | H35: 46085.479 | I35: 46085.479
A36: 0004 (REGISTRADOR LEFORT) | B36: Registrador Lefort Marmoleado Memorandum | C36: LEFORT | D36: Registrador Lefort Marmoleado Memorandum | E36: [{'grupo': 'Características Generales:', 'caracteristicas': [{'texto': 'Marca:', 'valor': 'Lefort '}, {'texto': 'Artículo:', 'valor': 'Registrador '}, {'texto': 'Tipo:', 'valor': 'Marmoleado '}]}] | F36: ['https://contenidos.exel.com.mx/ImagenesProductos/LF/LFPREGAB013_zoom.jpg'] | G36: t | H36: 46085.479 | I36: 46085.479
A37: 001297 | B37: CINTA KORES EPSON RC30 MORADO | C37: KORES | D37: <table border="0" cellpadding="0" cellspacing="0" width="776" style="border-collapse: collapse;width:582pt"> <tbody> <tr height="undefined" style="height:15.0pt"> <td height="20" class="xl65" width="776" style="height:15.0pt;width:582pt"> K cinta 459&nbsp;</td></tr></tbody></table> | E37: [{'grupo': 'Especificaciones Generales', 'caracteristicas': [{'texto': 'Detalle:', 'valor': 'Cinta Kores EpsonRC30 Morado'}]}] | F37: ['https://contenidos.exel.com.mx/ImagenesProductos/KRPCINAD046_zoom.jpg'] | G37: t | H37: 46085.479 | I37: 46085.479
A38: 001587 | B38: CINTA KORES P/BROTHER X10 MAQUINA ELECTRICA | C38: KORES | D38: <table border="0" cellpadding="0" cellspacing="0" width="776" style="border-collapse: collapse;width:582pt"> <tbody> <tr height="undefined" style="height:30.0pt"> <td height="40" class="xl65" width="776" style="height:30.0pt;width:582pt">Las cintas KORES son de una gran calidad debido a su intensidad y consistencia, f&#243;rmula&nbsp; de gran duraci&#243;n, resistentes y seguras.</td></tr></tbody></table> | E38: [{'grupo': 'Especificaciones Generales', 'caracteristicas': [{'texto': 'Detalle:', 'valor': 'Cinta Kores p /Brother X10 Maquina Electrica'}]}] | F38: ['https://contenidos.exel.com.mx/ImagenesProductos/KRPCINAD044_zoom.jpg'] | G38: t | H38: 46085.479 | I38: 46085.479
A39: 001907 | B39: CINTA P/CALCULADORA KORES NEGRO-ROJO 3.0CMS DIAMETRO | C39: KORES | D39: <table border="0" cellpadding="0" cellspacing="0" width="776" style="border-collapse: collapse;width:582pt"> <tbody> <tr height="undefined" style="height:15.0pt"> <td height="20" class="xl65" width="776" style="height:15.0pt;width:582pt"> K cinta para calculadora Secretary 255</td></tr></tbody></table> | E39: [{'grupo': 'Especificaciones Generales', 'caracteristicas': [{'texto': 'Detalle:', 'valor': 'Cinta P/Calculadora Kores'}, {'texto': 'Color:', 'valor': 'Negro-Rojo '}]}] | F39: ['https://contenidos.exel.com.mx/ImagenesProductos/KRPCINAD043_zoom.jpg'] | G39: t | H39: 46085.479 | I39: 46085.479
A40: 001R00600 | B40: Limpiador en Cinta Xerox 001R00600 60000 páginas | C40: XEROX | D40: Los artículos de mantenimiento de Xerox están diseñados para mantener su equipo Xerox operando de manera eficiente y para proporcionar la mejor calidad. | G40: t | H40: 46085.479 | I40: 46085.479
A41: 001R00610 | B41: Cinta Transferencia Xerox 001R00610 para WorkCentre 7120/7125 200000 páginas | C41: XEROX | D41: Xerox ofrece estos suministros desarrollados específicamente para mantener al equipo de Xerox funcionando en un rendimiento óptimo. | E41: [{'grupo': 'Especificaciones Generales', 'caracteristicas': [{'texto': 'Detalle:', 'valor': 'CINTA XEROX TRANSFERENCIA WORKCENTRE 7120/7125'}]}] | F41: ['https://contenidos.exel.com.mx/ImagenesProductos/XE/XECCINAD005_zoom.jpg'] | G41: t | H41: 46085.479 | I41: 46085.479
A42: 001R00613 | B42: LIMPIADOR CORREA XEROX 160K PAGINAS WC 7525/7530/753 | C42: XEROX | D42: Xerox ofrece estos suministros desarrollados específicamente para mantener al equipo de Xerox funcionando en un rendimiento óptimo. | E42: [{'grupo': 'Especificaciones Generales', 'caracteristicas': [{'texto': 'Productos compatibles', 'valor': 'WorkCentre 7525/7530/7535/7545/7556, 7830/7835/7845/7855, 7970/7970i, 7830i/7835i/7845i/7855i'}, {'texto': 'Tecnología de impresión\t', 'valor': 'Láser'}, {'texto': 'Capacidad', 'valor': '160,000'}, {'texto': 'Peso del paquete\t', 'valor': '453 g'}, {'texto': 'Profundidad de la caja\t', 'valor': '53,3 cm'}, {'texto': 'Altura de la caja\t', 'valor': '12,7 cm'}]}] | F42: ['https://contenidos.exel.com.mx/ImagenesProductos/XE/XECLIMAB003_zoom.jpg'] | G42: t | H42: 46085.479 | I42: 46085.479
A43: 001R00623 | B43: Limpiador para Banda de Transferencia Xerox 160K AltaLink C8130/35/45/55/70 B8145/55/70 | C43: XEROX | D43: El limpiador de banda de transferencia AltaLink C8130 / 35/45/55/70 B8145 / 55/70 está especialmente formulado y probado para proporcionar la mejor calidad de imagen y la impresión más confiable que pueda contar página tras página. Los consumibles originales de Xerox y los equipos de Xerox están hechos el uno para el otro. No aceptes imitaciones. | E43: [{'grupo': 'Características Generales:', 'caracteristicas': [{'texto': 'Marca:', 'valor': 'Xerox '}, {'texto': 'Artículo:', 'valor': 'Limpiador para Banda de Transferencia'}, {'texto': 'Capacidad:', 'valor': '160,000'}, {'texto': 'Compatibilidad:', 'valor': 'AltaLink C8130/35/45/55/70 y B8145/55/70'}]}] | F43: ['https://contenidos.exel.com.mx/ImagenesProductos/XECLIMAB006_zoom.jpg'] | G43: t | H43: 46085.479 | I43: 46085.479
A44: 003M00360 | B44: Papel Cortado Xerox Premium Azul Carta 97% Blancura 75Grs Caja C/5000 hojas | C44: XEROX | D44: Papel Cortado Xerox Premium Azul Carta 97% Blancura 75Grs Caja C/5000 hojas | G44: t | H44: 46085.479 | I44: 46085.479
A45: 003R75121 | B45: Papel Cortado Xerox Bond Digital Doble Carta 75gr Blancura 99% C/2500 Hojas | C45: XEROX | D45: Papel con Máxima Blancura y excelente calidad, con gran desempeño en equipos de impresión en alto volumen, ideal para trabajos especiales. | E45: [{'grupo': 'Características Generales:', 'caracteristicas': [{'texto': 'Marca:', 'valor': 'Xerox'}, {'texto': 'Artículo:', 'valor': 'Papel bond'}, {'texto': 'Tamaño:', 'valor': 'Doble Carta'}, {'texto': 'Cantidad', 'valor': 'Caja con 2,500 hojas'}, {'texto': 'Uso:', 'valor': 'Laser Inkjet, Digital Fotocopiado, Escolar, Oficinas'}, {'texto': 'Blancura:', 'valor': '99%'}, {'texto': 'Gramaje:', 'valor': '75 grs./m2'}]}] | F45: ['https://contenidos.exel.com.mx/ImagenesProductos/XE/XECPAPAE060_zoom.jpg', 'https://contenidos.exel.com.mx/ImagenesProductos/XE/XECPAPAE060_2_zoom.jpg'] | G45: t | H45: 46085.479 | I45: 46085.479
A46: 004 CAJA GEO | B46: CAJA GEO ARCHIVO CARTON CARTA 50X31X25 CM C/20 | C46: GEO | D46: CAJA GEO ARCHIVO CARTON CARTA 50X31X25 CM C/20 | E46: [{'grupo': 'Descripción', 'caracteristicas': [{'texto': 'Tamaño', 'valor': 'Carta'}, {'texto': 'Medidas', 'valor': '50 x 31 x 25 cm'}, {'texto': 'Material', 'valor': 'Cartón'}]}] | G46: t | H46: 46085.479 | I46: 46085.479
A47: 005 (CAJA GEO OFICIO) | B47: CAJA GEO ARCHIVO CARTON OFICIO 50X35X25 CM C/20 | C47: GEO | D47: CAJA GEO ARCHIVO CARTON OFICIO 50X35X25 CM C/20 | E47: [{'grupo': 'Descripción', 'caracteristicas': [{'texto': 'Tamaño', 'valor': 'Oficio'}, {'texto': 'Medidas', 'valor': '50 x 35 x 25 cm'}, {'texto': 'Material', 'valor': 'Cartón'}]}] | G47: t | H47: 46085.479 | I47: 46085.479
A48: 0064 (LIBRETA ESTRELLA) | B48: LIBRETA ESTRELLA 1/4 PASTA DURA ITALIANA RAYA 96 HJS | C48: ESTRELLA | D48: LIBRETA ESTRELLA 1/4 PASTA DURA ITALIANA RAYA 96 HJS | E48: [{'grupo': 'Especificaciones Generales', 'caracteristicas': [{'texto': 'Detalle:', 'valor': 'LIBRETA ESTRELLA DE 1/4 P.DURA F.ITALIANA RAYA 96 HJS'}]}] | F48: ['https://contenidos.exel.com.mx/ImagenesProductos/EAPLIRAB021_zoom.png'] | G48: t | H48: 46085.479 | I48: 46085.479
A49: 0065 | B49: LIBRETA ESTRELLA 1/4 PASTA DURA ITALIANA RAYA 144 HJS | C49: ESTRELLA | D49: LIBRETA ESTRELLA 1/4 PASTA DURA ITALIANA RAYA 144 HJS | E49: [{'grupo': 'Especificaciones Generales', 'caracteristicas': [{'texto': 'Detalle:', 'valor': 'LIBRETA ESTRELLA DE 1/4 P.DURA F.ITALIANA RAYA 144 HJS'}]}] | F49: ['https://contenidos.exel.com.mx/ImagenesProductos/EAPLIRAB022_zoom.png'] | G49: t | H49: 46085.479 | I49: 46085.479
A50: 0066 | B50: LIBRETA ESTRELLA 1/4 PASTA DURA ITALIANA RAYA 192 HJS | C50: ESTRELLA | D50: LIBRETA ESTRELLA 1/4 PASTA DURA ITALIANA RAYA 192 HJS | E50: [{'grupo': 'Especificaciones Generales', 'caracteristicas': [{'texto': 'Detalle:', 'valor': 'LIBRETA ESTRELLA DE 1/4 P.DURA F.ITALIANA RAYA 192 HJS'}]}] | F50: ['https://contenidos.exel.com.mx/ImagenesProductos/EAPLIRAB023_zoom.png'] | G50: t | H50: 46085.479 | I50: 46085.479
A51: 006R01046 | B51: Tóner Xerox 2 Botellas 5% de Cobertura 60000 Páginas (5735/40/45/55) | C51: XEROX | D51: Adquiere tóner Xerox de color negro con un gran rendimiento y obtén las mejor impresiones con cosumibles Xerox. | E51: [{'grupo': 'Detalles técnicos', 'caracteristicas': [{'texto': 'Color', 'valor': 'no'}]}, {'grupo': 'Calidad de impresión', 'caracteristicas': [{'texto': 'Colores de impresión', 'valor': 'Negro'}]}, {'grupo': 'Características Generales:', 'caracteristicas': [{'texto': 'Marca:', 'valor': 'Xerox'}, {'texto': 'Artículo:', 'valor': 'Tóner '}, {'texto': 'Capacidad:', 'valor': '60,000 Páginas '}, {'texto': 'Cantidad:', 'valor': '2 Botellas'}, {'texto': 'Compatibilidad:', 'valor': 'WorkCentre 5735/40/45/55'}]}] | F51: ['https://contenidos.exel.com.mx/ImagenesProductos/XECTONAB126_zoom.png'] | G51: t | H51: 46085.479 | I51: 46085.479
A52: 006R01160 | B52: TONER XEROX NEGRO (RENDIMIENTO 30000 IMPRESIO | C52: XEROX | D52: Adquiere tóner Xerox de color negro con un gran rendimiento de 30,000 páginas y obtén las mejor impresiones con cosumibles Xerox. | E52: [{'grupo': 'Especificaciones Generales', 'caracteristicas': [{'texto': 'Compatibilidad', 'valor': 'WorkCentre 5325/5330/5335'}, {'texto': 'Rendimiento', 'valor': '30,000 páginas'}]}] | F52: ['https://contenidos.exel.com.mx/ImagenesProductos/XE/XECTONAB518_zoom.jpg'] | G52: t | H52: 46085.479 | I52: 46085.479
A53: 006R01178 | B53: TONER XEROX WC PRO C3545 AMARILLO | C53: XEROX | D53: Adquiere tóner Xerox de color amarillo con un gran rendimiento de 16,000 páginas y obtén las mejor impresiones con cosumibles Xerox. | G53: t | H53: 46085.479 | I53: 46085.479
A54: 006R01182 | B54: Toner Xerox WorkCentre 123 128 Negro | C54: XEROX | D54: Adquiere tóner xerox Workcentre de color negro, que ofrece una calidad de impresión brillante consistente y un rendimiento superior. | E54: [{'grupo': 'Características Generales:', 'caracteristicas': [{'texto': 'Marca:', 'valor': 'Xerox'}, {'texto': 'Artículo:', 'valor': 'Toner'}, {'texto': 'Colores de impresión:', 'valor': 'Negro'}, {'texto': 'Compatibilidad:', 'valor': 'WorkCentre 123, 128.'}]}] | F54: ['https://contenidos.exel.com.mx/ImagenesProductos/XECTONAB227_zoom.jpg'] | G54: t | H54: 46085.479 | I54: 46085.479
A55: 006R01238 | B55: TONER XEROX 6204 NEGRO | C55: XEROX | D55: <div>Xerox cartucho de tóner, esta especialmente formulado y probado para proporcionar la mejor calidad de imagen y la impresión más confiable que puede obtener página tras página. </div><div></div> | G55: t | H55: 46085.479 | I55: 46085.479
A56: 006R01271 | B56: TONER XEROX AMARILLO WORKCENTRE 7132W 8000 | C56: XEROX | D56: <div>Adquiere tóner xerox workcentre de color amarillo, con un rendimiento de 7,000 páginas, que ofrece una calidad de impresión brillante consistente y un rendimiento superior.</div><div></div> | E56: [{'grupo': 'Detalles técnicos', 'caracteristicas': [{'texto': 'Color', 'valor': 'si'}]}, {'grupo': 'Calidad de impresión', 'caracteristicas': [{'texto': 'Producción de papel', 'valor': '7000 páginas'}, {'texto': 'Tecnología de impresión', 'valor': 'Laser'}, {'texto': 'Colores de impresión', 'valor': 'Amarillo'}]}] | F56: ['https://contenidos.exel.com.mx/ImagenesProductos/006R01271_zoom.jpg'] | G56: t | H56: 46085.479 | I56: 46085.479
A57: 006R01272 | B57: TONER XEROX MAGENTA WORKCENTRE 7132W 8000 | C57: XEROX | D57: Adquiere tóner xerox workcentre de color magenta, con un rendimiento de 7,000 páginas, que ofrece una calidad de impresión brillante consistente y un rendimiento superior. | E57: [{'grupo': 'Detalles técnicos', 'caracteristicas': [{'texto': 'Color', 'valor': 'si'}]}, {'grupo': 'Calidad de impresión', 'caracteristicas': [{'texto': 'Producción de papel', 'valor': '7000 páginas'}, {'texto': 'Tecnología de impresión', 'valor': 'Laser'}, {'texto': 'Colores de impresión', 'valor': 'magenta'}]}] | F57: ['https://contenidos.exel.com.mx/ImagenesProductos/006R01272_zoom.jpg'] | G57: t | H57: 46085.479 | I57: 46085.479
A58: 006R01276 | B58: TONER XEROX WORKCENTRE 4150 20k | C58: XEROX | D58: <div></div><div>Adquiere tóner xerox workcentre de color negro, con un rendimiento de 20,000 páginas, que ofrece una calidad de impresión brillante consistente y un rendimiento superior.</div> | E58: [{'grupo': 'Detalles técnicos', 'caracteristicas': [{'texto': 'Color', 'valor': 'si'}]}, {'grupo': 'Peso y dimensiones', 'caracteristicas': [{'texto': 'Producción de papel', 'valor': '20000 páginas'}, {'texto': 'Colores de impresión', 'valor': 'Negro'}, {'texto': 'Dimensiones (Ancho x Profundidad x Altura)', 'valor': '424 x 281 x 179 mm'}]}] | F58: ['https://contenidos.exel.com.mx/ImagenesProductos/006R01276_zoom.jpg'] | G58: t | H58: 46085.479 | I58: 46085.479
A59: 006R01319 | B59: TONER XEROX NEGRO 24K | C59: XEROX | D59: <div>Adquiere tóner Xerox con un gran rendimiento de 24,300 páginas y obtén las mejor impresiones con cosumibles Xerox. </div><div></div> | E59: [{'grupo': 'Detalles técnicos', 'caracteristicas': [{'texto': 'Tipo', 'valor': 'toner'}]}, {'grupo': 'Calidad de impresión', 'caracteristicas': [{'texto': 'Producción de papel', 'valor': '24300 páginas'}, {'texto': 'Tecnología de impresión', 'valor': 'Laser'}, {'texto': 'Colores de impresión', 'valor': 'Negro'}, {'texto': 'Productos compatibles', 'valor': 'WorkCentre 7232, 7242'}, {'texto': 'Cantidad', 'valor': '1'}]}] | F59: ['https://contenidos.exel.com.mx/ImagenesProductos/006R01319_zoom.jpg'] | G59: t | H59: 46085.479 | I59: 46085.479
A60: 006R01400 | B60: TONER XEROX AMARILLO WC 7425/7428/7435 | C60: XEROX | D60: Adquiere tóner Xerox de color amarillo con un gran rendimiento y obtén las mejor impresiones con cosumibles Xerox. | E60: [{'grupo': 'Detalles técnicos', 'caracteristicas': [{'texto': 'Color', 'valor': 'si'}, {'texto': 'Tipo', 'valor': 'toner'}]}, {'grupo': 'Calidad de impresión', 'caracteristicas': [{'texto': 'Producción de papel', 'valor': '15000 páginas'}, {'texto': 'Tecnología de impresión', 'valor': 'Laser'}, {'texto': 'Colores de impresión', 'valor': 'Amarillo'}, {'texto': 'Productos compatibles', 'valor': 'WorkCentre 7425/7428/7435'}, {'texto': 'Cantidad', 'valor': '1'}]}] | F60: ['https://contenidos.exel.com.mx/ImagenesProductos/006R01400_zoom.jpg'] | G60: t | H60: 46085.479 | I60: 46085.479
A61: 006R01401 | B61: TONER XEROX MAGENTA WC 7425/7428/7435 | C61: XEROX | D61: Tóner Xerox de color magenta, con un rendimiento de 15,000 páginas con tecnología de impresión de láser. | E61: [{'grupo': 'Detalles técnicos', 'caracteristicas': [{'texto': 'Color', 'valor': 'si'}, {'texto': 'Tipo', 'valor': 'toner'}]}, {'grupo': 'Calidad de impresión', 'caracteristicas': [{'texto': 'Producción de papel', 'valor': '15000 páginas'}, {'texto': 'Tecnología de impresión', 'valor': 'Laser'}, {'texto': 'Colores de impresión', 'valor': 'magenta'}, {'texto': 'Productos compatibles', 'valor': 'WorkCentre 7425/7428/7435'}, {'texto': 'Cantidad', 'valor': '1'}]}] | F61: ['https://contenidos.exel.com.mx/ImagenesProductos/006R01401_zoom.jpg'] | G61: t | H61: 46085.479 | I61: 46085.479
A62: 006R01402 | B62: TONER XEROX CYAN WC 7425/7428/7435 | C62: XEROX | D62: Tóner Xerox de color cyan, con un rendimiento de 15,000 páginas con tecnología de impresión de láser. | G62: t | H62: 46085.479 | I62: 46085.479
A63: 006R01404 | B63: TONER XEROX CYAN 34000 PAG | C63: XEROX | D63: Adquiere tóner xerox de color cyan con un rendimiento de 34,000 páginas que ofrece una calidad de impresión brillante consistente y un rendimiento superior. | E63: [{'grupo': 'Detalles técnicos', 'caracteristicas': [{'texto': 'Tipo', 'valor': 'cartucho'}]}, {'grupo': 'Calidad de impresión', 'caracteristicas': [{'texto': 'Producción de papel', 'valor': '34000 páginas'}, {'texto': 'Tecnología de impresión', 'valor': 'Laser'}, {'texto': 'Colores de impresión', 'valor': 'Cyan'}, {'texto': 'Productos compatibles', 'valor': 'WorkCentre 7755/7765/7775'}, {'texto': 'Cantidad', 'valor': '1'}]}] | F63: ['https://contenidos.exel.com.mx/ImagenesProductos/006R01404_zoom.jpg'] | G63: t | H63: 46085.479 | I63: 46085.479
A64: 006R01405 | B64: TONER XEROX MAGENTA 34000 PAG | C64: XEROX | D64: <div></div><div>Adquiere tóner xerox de color magenta con un rendimiento de 31,700 páginas que ofrece una calidad de impresión brillante consistente y un rendimiento superior.</div> | E64: [{'grupo': 'Detalles técnicos', 'caracteristicas': [{'texto': 'Tipo', 'valor': 'cartucho'}]}, {'grupo': 'Calidad de impresión', 'caracteristicas': [{'texto': 'Producción de papel', 'valor': '31700 páginas'}, {'texto': 'Tecnología de impresión', 'valor': 'Laser'}, {'texto': 'Colores de impresión', 'valor': 'Magenta'}, {'texto': 'Productos compatibles', 'valor': 'WorkCentre 7755/7765/7775'}, {'texto': 'Cantidad', 'valor': '1'}]}] | G64: t | H64: 46085.479 | I64: 46085.479
A65: 006R01406 | B65: TONER XEROX AMARILLO 34000 PAG | C65: XEROX | D65: Adquiere tóner xerox de color amarillo con un rendimiento de 34,000 páginas que ofrece una calidad de impresión brillante consistente y un rendimiento superior. | E65: [{'grupo': 'Especificaciones Generales', 'caracteristicas': [{'texto': 'Compatibilidad', 'valor': 'WorkCentre 7755/7765/7775'}, {'texto': 'Rendimiento', 'valor': '34,000 páginas'}]}] | F65: ['https://contenidos.exel.com.mx/ImagenesProductos/XE/XECTONAB464_zoom.jpg'] | G65: t | H65: 46085.479 | I65: 46085.479
A66: 006R01461 | B66: TONER XEROX NEGRO WC7120 | C66: XEROX | D66: Adquiere tóner xerox de color negro WC7120 con un rendimiento de 22,000 páginas que ofrece una calidad de impresión brillante consistente y un rendimiento superior. | E66: [{'grupo': 'Detalles técnicos', 'caracteristicas': [{'texto': 'Tipo', 'valor': 'toner'}]}, {'grupo': 'Calidad de impresión', 'caracteristicas': [{'texto': 'Producción de papel', 'valor': '22000 páginas'}, {'texto': 'Colores de impresión', 'valor': 'Negro'}, {'texto': 'Productos compatibles', 'valor': 'WorkCentre 7120'}, {'texto': 'Cantidad', 'valor': '1'}]}] | F66: ['https://contenidos.exel.com.mx/ImagenesProductos/006R01461_zoom.jpg'] | G66: t | H66: 46085.479 | I66: 46085.479
A67: 006R01462 | B67: TONER XEROX AMARILLO WC7120 | C67: XEROX | D67: Adquiere tóner xerox de color amarillo con un rendimiento de 15,000 páginas que ofrece una calidad de impresión brillante consistente y un rendimiento superior. | E67: [{'grupo': 'Detalles técnicos', 'caracteristicas': [{'texto': 'Tipo', 'valor': 'toner'}]}, {'grupo': 'Calidad de impresión', 'caracteristicas': [{'texto': 'Producción de papel', 'valor': '15000 páginas'}, {'texto': 'Colores de impresión', 'valor': 'Amarillo'}, {'texto': 'Productos compatibles', 'valor': 'WorkCentre7120'}, {'texto': 'Cantidad', 'valor': '1'}]}] | F67: ['https://contenidos.exel.com.mx/ImagenesProductos/006R01462_zoom.jpg'] | G67: t | H67: 46085.479 | I67: 46085.479
A68: 006R01464 | B68: TONER XEROX CYAN WC7120 | C68: XEROX | D68: Adquiere tóner xerox de color cyan con un rendimiento de 15,000 páginas que ofrece una calidad de impresión brillante consistente y un rendimiento superior. | E68: [{'grupo': 'Detalles técnicos', 'caracteristicas': [{'texto': 'Tipo', 'valor': 'toner'}]}, {'grupo': 'Calidad de impresión', 'caracteristicas': [{'texto': 'Producción de papel', 'valor': '15000 páginas'}, {'texto': 'Colores de impresión', 'valor': 'cyan'}, {'texto': 'Productos compatibles', 'valor': 'WorkCentre7120'}, {'texto': 'Cantidad', 'valor': '1'}]}] | F68: ['https://contenidos.exel.com.mx/ImagenesProductos/006R01464_zoom.jpg'] | G68: t | H68: 46085.479 | I68: 46085.479
A69: 006R01480 | B69: Tóner Xerox X800/1000 1 Bote Color Negro | C69: XEROX | D69: Tóner Xerox X800/1000 1 Bote Color Negro | E69: [{'grupo': 'Características Generales:', 'caracteristicas': [{'texto': 'Marca:', 'valor': 'Xerox'}, {'texto': 'Artículo:', 'valor': 'Tóner'}, {'texto': 'Color:', 'valor': 'Negro'}, {'texto': 'Rendimiento:', 'valor': '3000 Páginas'}, {'texto': 'Compatibilidad:', 'valor': 'X800/1000'}]}] | F69: ['https://contenidos.exel.com.mx/ImagenesProductos/XE/XECTONAB498_zoom.jpg'] | G69: t | H69: 46085.479 | I69: 46085.479
A70: 006R01481 | B70: TONER XEROX X800/1000 CYAN 1BOTE | C70: XEROX | D70: TONER XEROX X800/1000 CYAN 1BOTE | E70: [{'grupo': 'Características', 'caracteristicas': [{'texto': 'Color', 'valor': 'Cyan'}, {'texto': 'Compatibilidad', 'valor': 'X800/1000'}, {'texto': 'Rendimiento aproximado', 'valor': '25,000 páginas'}]}] | G70: t | H70: 46085.479 | I70: 46085.479
A71: 006R01482 | B71: TONER XEROX X800/1000 MAGENTA 1BOTE | C71: XEROX | D71: Adquiere tóner Xerox de color magenta con un rendimiento de 25,000 páginas y obtén las mejor impresiones con cosumibles Xerox. | E71: [{'grupo': 'Características', 'caracteristicas': [{'texto': 'Color', 'valor': 'Magenta'}, {'texto': 'Compatibilidad', 'valor': 'X800/1000'}, {'texto': 'Rendimiento aproximado', 'valor': '25,000 páginas'}]}] | F71: ['https://contenidos.exel.com.mx/ImagenesProductos/XE/XECTONAB500_zoom.jpg'] | G71: t | H71: 46085.479 | I71: 46085.479
A72: 006R01483 | B72: TONER XEROX X800/1000 AMARILLO 1BOTE | C72: XEROX | D72: Adquiere tóner Xerox de color amarillo con un rendimiento de 25,000 páginas y obtén las mejor impresiones con cosumibles Xerox. | E72: [{'grupo': 'Características', 'caracteristicas': [{'texto': 'Color', 'valor': 'Amarillo'}, {'texto': 'Compatibilidad', 'valor': 'X800/1000'}, {'texto': 'Rendimiento aproximado', 'valor': '25,000 páginas'}]}] | F72: ['https://contenidos.exel.com.mx/ImagenesProductos/XE/XECTONAB501_zoom.jpg'] | G72: t | H72: 46085.479 | I72: 46085.479
A73: 006R01517 | B73: TONER XEROX WC7545/75567525/7530/7535 NEGRO | C73: XEROX | D73: Adquiere tóner Xerox de color negro con un rendimiento de 26,000 páginas y obtén las mejor impresiones con cosumibles Xerox. | E73: [{'grupo': 'Especificaciones Generales', 'caracteristicas': [{'texto': 'Compatibilidad', 'valor': 'WorkCentre 7525/7530/7535/7545/7556'}, {'texto': 'Rendimiento', 'valor': '26,000 páginas'}]}] | F73: ['https://contenidos.exel.com.mx/ImagenesProductos/006R01517_zoom.jpg'] | G73: t | H73: 46085.479 | I73: 46085.479
A74: 006R01518 | B74: TONER XEROX WC7545/7556/7525/7530/7535 AMARILLO | C74: XEROX | D74: Adquiere tóner Xerox de color amarillo con un gran rendimiento de 15,000 páginas y obtén las mejor impresiones con cosumibles Xerox. | E74: [{'grupo': 'Especificaciones Generales', 'caracteristicas': [{'texto': 'Compatibilidad', 'valor': 'WorkCentre 7525/7530/7535/7545/7556'}, {'texto': 'Rendimiento', 'valor': '15,000 páginas'}]}] | F74: ['https://contenidos.exel.com.mx/ImagenesProductos/006R01518_zoom.jpg'] | G74: t | H74: 46085.479 | I74: 46085.479
A75: 006R01519 | B75: TONER XEROX WC7545/7556/7525/7530/7535 MAGENTA | C75: XEROX | D75: Adquiere tóner Xerox de color magenta con un gran rendimiento de 15,000 páginas y obtén las mejor impresiones con cosumibles Xerox. | E75: [{'grupo': 'Especificaciones Generales', 'caracteristicas': [{'texto': 'Compatibilidad', 'valor': 'WorkCentre 7525/7530/7535/7545/7556'}, {'texto': 'Rendimiento', 'valor': '15,000 páginas'}]}] | F75: ['https://contenidos.exel.com.mx/ImagenesProductos/006R01519_zoom.jpg'] | G75: t | H75: 46085.479 | I75: 46085.479
A76: 006R01520 | B76: TONER XEROX WC7545/75567525/7530/7535 CYAN | C76: XEROX | D76: Adquiere tóner Xerox de color cyan con un gran rendimiento de 15,000 páginas y obtén las mejor impresiones con cosumibles Xerox. | E76: [{'grupo': 'Especificaciones Generales', 'caracteristicas': [{'texto': 'Compatibilidad', 'valor': 'WorkCentre 7525/7530/7535/7545/7556'}, {'texto': 'Rendimiento', 'valor': '15,000 páginas'}]}] | F76: ['https://contenidos.exel.com.mx/ImagenesProductos/006R01520_zoom.jpg'] | G76: t | H76: 46085.479 | I76: 46085.479
A77: 006R01551 | B77: TONER XEROX NEGRO WC 5845/5855 76000 PGS | C77: XEROX | D77: <div>Está especialmente formulado y probado para proporcionar la mejor calidad de imagen y la impresión más confiable que pueda obtener página tras página.</div><div></div> | G77: t | H77: 46085.479 | I77: 46085.479
A78: 006R01573 | B78: TONER XEROX WC 5021 | C78: XEROX | D78: Tóner está especialmente formulado y probado para proporcionar la mejor calidad de imagen y la impresión más confiable que pueda obtener página tras página. Los suministros originales de Xerox y el equipo de Xerox están hechos el uno para el otro. | E78: [{'grupo': 'Características Generales:', 'caracteristicas': [{'texto': 'Marca:', 'valor': 'Xerox'}, {'texto': 'Artículo:', 'valor': 'Tóner'}, {'texto': 'Capacidad:', 'valor': '9,000 páginas'}, {'texto': 'Compatibilidad:', 'valor': 'WorkCentre 5021'}]}] | F78: ['https://contenidos.exel.com.mx/ImagenesProductos/XECTONAB536_zoom.jpg'] | G78: t | H78: 46085.479 | I78: 46085.479
A79: 006R01606 | B79: TONER XEROX NEGRO WC5945/5955 | C79: XEROX | D79: Adquiere tóner Xerox de color negro con un gran rendimiento y obtén las mejor impresiones con cosumibles Xerox. | E79: [{'grupo': 'Especificaciones Generales', 'caracteristicas': [{'texto': 'Detalle:', 'valor': 'TONER XEROX NEGRO PARA WC5945/5955'}]}] | F79: ['https://contenidos.exel.com.mx/ImagenesProductos/XE/XECTONAB577_zoom.jpg'] | G79: t | H79: 46085.479 | I79: 46085.479
A80: 006R01683 | B80: Tóner Xerox 2 Botes C/U 44K AltaLink B80XX Color Negro | C80: XEROX | D80: Tóner Xerox 2 Botes C/U 44K AltaLink B80XX Color Negro | E80: [{'grupo': 'Especificaciones Generales', 'caracteristicas': [{'texto': 'Marca:', 'valor': 'XEROX'}, {'texto': 'Dimensiones:', 'valor': '(L 46, A 20, A 8.5,) cm'}, {'texto': 'Peso:', 'valor': '1.5 Kg'}]}] | F80: ['https://contenidos.exel.com.mx/ImagenesProductos/XE/XECTONAB629_zoom.jpg'] | G80: t | H80: 46085.479 | I80: 46085.479
A81: 006R01701 | B81: Toner Xerox Alatlink Negro | C81: XEROX | D81: Toner Xerox Alatlink Negro | E81: [{'grupo': 'Especificaciones Generales', 'caracteristicas': [{'texto': 'Marca:', 'valor': 'Xerox'}, {'texto': 'Articulo:', 'valor': 'Toner'}, {'texto': 'Color:', 'valor': 'Negro'}, {'texto': 'Dimensiones:', 'valor': '(L.45.7199 A.8.2549 A.8.2549)cm'}, {'texto': 'Peso:', 'valor': '0.9997 Kg'}]}] | F81: ['https://contenidos.exel.com.mx/ImagenesProductos/XE/XECTONAB630_zoom.jpg'] | G81: t | H81: 46085.479 | I81: 46085.479
A82: 006R01702 | B82: Toner Xerox Altalink Cyan | C82: XEROX | D82: Toner Xerox Altalink Cyan | E82: [{'grupo': 'Especificaciones Generales', 'caracteristicas': [{'texto': 'Marca:', 'valor': 'Xerox'}, {'texto': 'Articulo:', 'valor': 'Toner'}, {'texto': 'Color:', 'valor': 'Cyan'}, {'texto': 'Dimensiones:', 'valor': '(L.45.7199 A.76.199 A.6.4819)cm'}, {'texto': 'Peso:', 'valor': '0.6577 Kg'}]}] | F82: ['https://contenidos.exel.com.mx/ImagenesProductos/XE/XECTONAB631_zoom.jpg'] | G82: t | H82: 46085.479 | I82: 46085.479
A83: 006R01703 | B83: Toner Xerox Altalink Magenta | C83: XEROX | D83: Toner Xerox Altalink Magenta | E83: [{'grupo': 'Especificaciones Generales', 'caracteristicas': [{'texto': 'Marca:', 'valor': 'Xerox'}, {'texto': 'Articulo:', 'valor': 'Toner'}, {'texto': 'Color:', 'valor': 'Magenta'}, {'texto': 'Dimensiones:', 'valor': '(L.45.7199 A.76.199 A.6.9849)cm'}, {'texto': 'Peso:', 'valor': '0.6577 Kg'}]}] | F83: ['https://contenidos.exel.com.mx/ImagenesProductos/XE/XECTONAB632_zoom.jpg'] | G83: t | H83: 46085.479 | I83: 46085.479
A84: 006R01704 | B84: Toner Xerox Altalink Amarillo | C84: XEROX | D84: Toner Xerox Altalink Amarillo | E84: [{'grupo': 'Especificaciones Generales', 'caracteristicas': [{'texto': 'Marca:', 'valor': 'Xerox'}, {'texto': 'Articulo:', 'valor': 'Toner'}, {'texto': 'Color:', 'valor': 'Amarillo'}, {'texto': 'Dimensiones:', 'valor': '(L.45.7199 A.76.199 A.6.9849 )cm'}, {'texto': 'Peso:', 'valor': '0.6577Kg'}]}] | F84: ['https://contenidos.exel.com.mx/ImagenesProductos/XE/XECTONAB633_zoom.jpg'] | G84: t | H84: 46085.479 | I84: 46085.479
A85: 006R01731 | B85: Toner Xerox Negro para B1025 | C85: XEROX | D85: Toner Xerox Negro para B1025 | E85: [{'grupo': 'Especificaciones Generales', 'caracteristicas': [{'texto': 'Marca:', 'valor': 'Xerox'}, {'texto': 'Articulo:', 'valor': 'Toner'}, {'texto': 'Color:', 'valor': 'Negro'}, {'texto': 'Uso:', 'valor': 'Para B1025'}, {'texto': 'Dimensiones:', 'valor': '20 x 9 x 10 cm'}, {'texto': 'Peso:', 'valor': '0.3 kg'}]}] | F85: ['https://contenidos.exel.com.mx/ImagenesProductos/XE/XECTONAB668_zoom.jpg'] | G85: t | H85: 46085.479 | I85: 46085.479
A86: 006R01754 | B86: Tóner Xerox AltaLink C8130/C8135 59K Páginas Color Negro | C86: XEROX | D86: Tóner Xerox AltaLink C8130/C8135 59K Páginas Color Negro | E86: [{'grupo': 'Características Generales:', 'caracteristicas': [{'texto': 'Marca:', 'valor': 'Xerox '}, {'texto': 'Artículo:', 'valor': 'Tóner '}, {'texto': 'Color:', 'valor': 'Negro'}, {'texto': 'Capacidad:', 'valor': '59K Páginas'}, {'texto': 'Compatibilidad:', 'valor': 'AltaLink C8130/C8135'}]}] | F86: ['https://contenidos.exel.com.mx/ImagenesProductos/XECTONAB707_zoom.jpg'] | G86: t | H86: 46085.479 | I86: 46085.479
A87: 006R01755 | B87: Tóner Xerox AltaLink C8130/C8135 28K Páginas Color Cian | C87: XEROX | D87: Tóner Xerox AltaLink C8130/C8135 28K Páginas Color Cian | E87: [{'grupo': 'Características Generales:', 'caracteristicas': [{'texto': 'Marca:', 'valor': 'Xerox'}, {'texto': 'Artículo:', 'valor': 'Tóner '}, {'texto': 'Color:', 'valor': 'Cian'}, {'texto': 'Capacidad:', 'valor': '28K Páginas'}, {'texto': 'Compatibilidad:', 'valor': 'AltaLink C8130/C8135'}]}] | F87: ['https://contenidos.exel.com.mx/ImagenesProductos/XECTONAB704_zoom.jpg'] | G87: t | H87: 46085.479 | I87: 46085.479
A88: 006R01756 | B88: Tóner Xerox AltaLink C8130/C8135 28K Páginas Color Magenta | C88: XEROX | D88: Tóner Xerox AltaLink C8130/C8135 28K Páginas Color Magenta | E88: [{'grupo': 'Características Generales:', 'caracteristicas': [{'texto': 'Marca:', 'valor': 'Xerox '}, {'texto': 'Artículo:', 'valor': 'Tóner '}, {'texto': 'Color:', 'valor': 'Magenta'}, {'texto': 'Capacidad:', 'valor': ' 28K Páginas'}, {'texto': 'Compatibilidad:', 'valor': 'AltaLink C8130/C8135'}]}] | F88: ['https://contenidos.exel.com.mx/ImagenesProductos/XECTONAB705_zoom.jpg'] | G88: t | H88: 46085.479 | I88: 46085.479
A89: 006R01757 | B89: Tóner Xerox AltaLink C8130/C8135 28K Páginas Color Amarillo | C89: XEROX | D89: Tóner Xerox AltaLink C8130/C8135 28K Páginas Color Amarillo | E89: [{'grupo': 'Características Generales:', 'caracteristicas': [{'texto': 'Marca:', 'valor': 'Xerox '}, {'texto': 'Artículo:', 'valor': 'Tóner '}, {'texto': 'Color:', 'valor': 'Amarillo'}, {'texto': 'Capacidad:', 'valor': '28K Páginas'}, {'texto': 'Compatibilidad:', 'valor': 'AltaLink C8130/C8135'}]}] | F89: ['https://contenidos.exel.com.mx/ImagenesProductos/XECTONAB706_zoom.jpg'] | G89: t | H89: 46085.479 | I89: 46085.479
... A133: 006R04647 | B133: Cartucho Xerox de toner amarillo de alta capacidad para equipo C625 | C133: XEROX | D133: Cartucho Xerox de toner amarillo de alta capacidad para equipo C625 | E133: [{'grupo': 'Características Generales:', 'caracteristicas': [{'texto': 'Marca:', 'valor': 'Xerox'}, {'texto': 'Artículo:', 'valor': 'Cartucho de Tóner'}, {'texto': 'Modelo:', 'valor': '006R04647'}, {'texto': 'Color:', 'valor': 'Amarillo'}, {'texto': 'Tipo:', 'valor': 'Alta Capacidad'}, {'texto': 'Compatibilidad:', 'valor': 'Xerox C625'}, {'texto': 'Rendimiento:', 'valor': '25 000 páginas'}]}] | F133: ['https://contenidos.exel.com.mx/ImagenesProductos/XE/XECTONAB751_zoom.jpg'] | G133: t | H133: 46085.479 | I133: 46085.479
A134: 006R04671 | B134: Toner Xerox de capacidad estandar para equipo B625 | C134: XEROX | D134: Toner Xerox de capacidad estandar para equipo B625 | G134: t | H134: 46085.479 | I134: 46085.479
A135: 006R04672 | B135: Tóner Xerox Alta Capacidad 25000 Páginas Color Negro para VersaLink B620/B625 | C135: XEROX | D135: Tóner Xerox Alta Capacidad 25000 Páginas Color Negro para VersaLink B620/B625 | E135: [{'grupo': 'Características Generales:', 'caracteristicas': [{'texto': 'Marca:', 'valor': 'Xerox'}, {'texto': 'Artículo:', 'valor': 'Tóner'}, {'texto': 'Modelo:', 'valor': '006R04672'}, {'texto': 'Capacidad:', 'valor': '25000 Páginas'}, {'texto': 'Color:', 'valor': 'Negro'}, {'texto': 'Compatibilidad:', 'valor': 'VersaLink B620/B625'}]}] | F135: ['https://contenidos.exel.com.mx/ImagenesProductos/XE/XECTONAB746_zoom.jpg'] | G135: t | H135: 46085.479 | I135: 46085.479
A136: 006R04673 | B136: Tóner Xerox Capacidad Extra Alta 42000 Páginas Color Negro para VersaLink B620/B625 | C136: XEROX | D136: Tóner Xerox Capacidad Extra Alta 42000 Páginas Color Negro para VersaLink B620/B625 | E136: [{'grupo': 'Características Generales:', 'caracteristicas': [{'texto': 'Marca:', 'valor': 'Xerox'}, {'texto': 'Artículo:', 'valor': 'Tóner'}, {'texto': 'Modelo:', 'valor': '006R04673'}, {'texto': 'Capacidad:', 'valor': '42000 Páginas'}, {'texto': 'Color:', 'valor': 'Negro'}, {'texto': 'Compatibilidad:', 'valor': 'VersaLink B620/B625'}]}] | F136: ['https://contenidos.exel.com.mx/ImagenesProductos/XE/XECTONAB747_zoom.jpg'] | G136: t | H136: 46085.479 | I136: 46085.479
A137: 006R04677 | B137: Cartucho Xerox 006R04677 Negro 2.400 Páginas | C137: XEROX | D137: Cartucho Xerox 006R04677 Negro 2.400 Páginas | G137: t | H137: 46085.479 | I137: 46085.479
A138: 006R04678 | B138: Cartucho Xerox 006R04678 Cyan 2.000 Páginas | C138: XEROX | D138: Cartucho Xerox 006R04678 Cyan 2.000 Páginas | G138: t | H138: 46085.479 | I138: 46085.479
A139: 006R04679 | B139: Cartucho Xerox 006R04679 Magenta 2.000 Páginas | C139: XEROX | D139: Cartucho Xerox 006R04679 Magenta 2.000 Páginas | E139: [{'grupo': 'Características Generales:', 'caracteristicas': [{'texto': 'Marca:', 'valor': 'Xerox'}, {'texto': 'Artículo:', 'valor': 'Cartucho'}, {'texto': 'Compatibilidad:', 'valor': 'C415V_DN, C410V_DN'}, {'texto': 'Capacidad del cartucho:', 'valor': 'Rendimiento estándar'}, {'texto': 'Rendimiento de impresión color:', 'valor': '2000 páginas'}, {'texto': 'Colores de impresión:', 'valor': 'Magenta'}, {'texto': 'Compatibilidad de marca:', 'valor': 'Xerox'}, {'texto': 'Tipo de suministro:', 'valor': 'Empaque individual'}, {'texto': 'Cantidad por caja:', 'valor': '1 pieza'}, {'texto': 'Ancho del paquete:', 'valor': '117 mm'}, {'texto': 'Profundidad del paquete:', 'valor': '185 mm'}, {'texto': 'Altura del paquete:', 'valor': '90.5 mm'}, {'texto': 'Peso del paquete:', 'valor': '285.8 g'}]}] | F139: ['https://contenidos.exel.com.mx/ImagenesProductos/XE/XECTONAB766_zoom.jpg'] | G139: t | H139: 46085.479 | I139: 46085.479
A140: 006R04680 | B140: Cartucho Xerox 006R04680 Amarillo 2.000 Páginas | C140: XEROX | D140: Cartucho Xerox 006R04680 Amarillo 2.000 Páginas | E140: [{'grupo': 'Características Generales:', 'caracteristicas': [{'texto': 'Marca:', 'valor': 'Xerox'}, {'texto': 'Artículo:', 'valor': 'Cartucho'}, {'texto': 'Compatibilidad:', 'valor': 'C415V_DN, C410V_DN'}, {'texto': 'Cantidad por paquete:', 'valor': '1 pieza'}, {'texto': 'Capacidad del cartucho:', 'valor': 'Rendimiento estándar'}, {'texto': 'Rendimiento de impresión color:', 'valor': '2000 páginas'}, {'texto': 'Tipo:', 'valor': 'Original'}, {'texto': 'Colores de impresión:', 'valor': 'Amarillo'}, {'texto': 'Compatibilidad de marca:', 'valor': 'Xerox'}, {'texto': 'Tipo de suministro:', 'valor': 'Empaque individual'}, {'texto': 'Cantidad por caja:', 'valor': '1 pieza'}, {'texto': 'Color del producto:', 'valor': 'Negro, Amarillo'}, {'texto': 'Ancho del paquete:', 'valor': '117 mm'}, {'texto': 'Profundidad del paquete:', 'valor': '185 mm'}, {'texto': 'Altura del paquete:', 'valor': '90.5 mm'}, {'texto': 'Peso del paquete:', 'valor': '285.8 g'}, {'texto': 'Cumplimiento de sustentabilidad:', 'valor': 'Sí'}]}] | F140: ['https://contenidos.exel.com.mx/ImagenesProductos/XE/XECTONAB767_zoom.jpg'] | G140: t | H140: 46085.479 | I140: 46085.479
A141: 006R04728 | B141: Cartucho de Tóner Xerox Capacidad Estándar 6000 Páginas Compatibilidad B410/B415 | C141: XEROX | D141: Cartucho de Tóner Xerox Capacidad Estándar 6000 Páginas Compatibilidad B410/B415 | E141: [{'grupo': 'Características Generales:', 'caracteristicas': [{'texto': 'Marca:', 'valor': 'Xerox'}, {'texto': 'Artículo:', 'valor': 'Cartucho de Tóner'}, {'texto': 'Modelo:', 'valor': '006R04728'}, {'texto': 'Rendimiento:', 'valor': '6000 Páginas'}, {'texto': 'Color:', 'valor': 'Negro'}, {'texto': 'Compatibilidad:', 'valor': 'VersaLink B410/B415'}]}] | F141: ['https://contenidos.exel.com.mx/ImagenesProductos/XE/XECTONAB744_zoom.jpg'] | G141: t | H141: 46085.479 | I141: 46085.479
A142: 006R04729 | B142: Tóner Xerox de Alta Capacidad Rendimiento 14000 Páginas para B410/B415 Negro | C142: XEROX | D142: Tóner Xerox de Alta Capacidad Rendimiento 14000 Páginas para B410/B415 Negro | E142: [{'grupo': 'Características Generales:', 'caracteristicas': [{'texto': 'Marca:', 'valor': 'Xerox'}, {'texto': 'Artículo:', 'valor': 'Tóner'}, {'texto': 'Modelo:', 'valor': '006R04729'}, {'texto': 'Color:', 'valor': 'Negro'}, {'texto': 'Rendimiento:', 'valor': '14000 páginas'}, {'texto': 'Compatibilidad:', 'valor': 'B410/B415'}]}] | F142: ['https://contenidos.exel.com.mx/ImagenesProductos/XE/XECTONAB738_zoom.jpg'] | G142: t | H142: 46085.479 | I142: 46085.479
A143: 006R04730 | B143: Tóner Xerox de Capacidad Extra Alta Rendimiento 25000 Páginas para B410/B415 Negro | C143: XEROX | D143: Tóner Xerox de Capacidad Extra Alta Rendimiento 25000 Páginas para B410/B415 Negro | E143: [{'grupo': 'Características Generales:', 'caracteristicas': [{'texto': 'Marca:', 'valor': 'Xerox'}, {'texto': 'Artículo:', 'valor': 'Tóner'}, {'texto': 'Modelo:', 'valor': '006R04730'}, {'texto': 'Color:', 'valor': 'Negro'}, {'texto': 'Rendimiento:', 'valor': '25000 Páginas'}, {'texto': 'Compatibilidad:', 'valor': 'B410/B415'}]}] | F143: ['https://contenidos.exel.com.mx/ImagenesProductos/XE/XECTONAB739_zoom.jpg'] | G143: t | H143: 46085.479 | I143: 46085.479
...

Sheet Hoja1
A1: cmarca
A2: 3M | B2: =VLOOKUP(A2,Hoja3!$B$2:$C$95,2,FALSE) -> https://images.icecat.biz/img/brand/thumb/206_d81d1d188e244538ab3082f8435acbd0.jpg
A3: ACCO | B3: =VLOOKUP(A3,Hoja3!$B$2:$C$95,2,FALSE) -> #N/A
A4: ACER | B4: =VLOOKUP(A4,Hoja3!$B$2:$C$95,2,FALSE) -> https://images.icecat.biz/img/brand/thumb/7_2e1091176d2d450eae2dce7506f1952f.jpg
A5: ACTECK | B5: =VLOOKUP(A5,Hoja3!$B$2:$C$95,2,FALSE) -> #N/A
A6: ACUACOLOR | B6: =VLOOKUP(A6,Hoja3!$B$2:$C$95,2,FALSE) -> #N/A
A7: ACUARELO | B7: =VLOOKUP(A7,Hoja3!$B$2:$C$95,2,FALSE) -> #N/A
A8: ADATA | B8: =VLOOKUP(A8,Hoja3!$B$2:$C$95,2,FALSE) -> https://images.icecat.biz/img/brand/thumb/2634_2a848859d95b45c98590f1c44384958e.jpg
A9: ADESSO | B9: =VLOOKUP(A9,Hoja3!$B$2:$C$95,2,FALSE) -> #N/A
A10: AINK | B10: =VLOOKUP(A10,Hoja3!$B$2:$C$95,2,FALSE) -> #N/A
A11: ALFRA | B11: =VLOOKUP(A11,Hoja3!$B$2:$C$95,2,FALSE) -> #N/A
A12: AMAZON | B12: =VLOOKUP(A12,Hoja3!$B$2:$C$95,2,FALSE) -> #N/A
A13: AMD | B13: =VLOOKUP(A13,Hoja3!$B$2:$C$95,2,FALSE) -> #N/A
... A199: ZOTAC | B199: =VLOOKUP(A199,Hoja3!$B$2:$C$95,2,FALSE) -> #N/A

Sheet Hoja2
A1: cmarca | B1: cimagen
A2: Swingline
A3: -
A4: 3 En 1
A5: 3I Corporation
A6: 3M | B6: https://images.icecat.biz/img/brand/thumb/206_d81d1d188e244538ab3082f8435acbd0.jpg
A7: 3M | B7: https://inishop.com/thumbs/SUP723.jpg
A8: 3M | B8: https://inishop.com/img/brand/thumb/804_0475cea0b61e4842aa61baa9c12edea7.jpg
A9: 3Nstar | B9: https://inishop.com/img/brand/thumb/18611_2e1846547a7845eaacc3d381f61f7e01.jpg
A10: 4Gamers
A11: Abell
A12: Abloy
A13: Absormex
A14: Accesspro | B14: https://inishop.com/img/brand/thumb/19849_04c0e1122efd485baf68c1182d5ebfca.jpg
A15: Accesspro
A16: Accesspro Industrial
A17: Acco
A18: Acer | B18: https://images.icecat.biz/img/brand/thumb/7_2e1091176d2d450eae2dce7506f1952f.jpg
A19: Acme
A20: Acteck
A21: Acti
A22: Actisense
A23: Acuacolor
A24: Acuarelo
A25: Adata | B25: https://images.icecat.biz/img/brand/thumb/2634_2a848859d95b45c98590f1c44384958e.jpg
A26: Adata | B26: https://images.icecat.biz/img/brand/thumb/32301_3243df0daeb740f998efd0a01bc129bb.jpg
A27: Ademco (Honeywell)
A28: Adesso | B28: https://inishop.com/img/brand/thumb/2817_db5fa942fc2640078996fc400d4fd629.jpg
A29: Adex
A30: Advancetec Industries Inc
A31: Aea
A32: Aerocool | B32: https://images.icecat.biz/img/brand/thumb/1935_406c04e90f78451e8cdd4a6a2a4c0e6f.jpg
A33: Afore
A34: Aink
A35: Airmar
A36: Airx
A37: Ajax
A38: Akubela
A39: Akuvox
A40: Alarm Controls-Assa Abloy
A41: Aleph
A42: Alerton
A43: Alex
A44: Alfra
A45: Allied Telesis | B45: https://images.icecat.biz/img/brand/thumb/49_8e89cb7fac62454a81797ce1e528cb76.jpg
A46: Altai Technologies | B46: https://inishop.com/img/brand/thumb/26489_6713ffd885f34d39a6540a1bdb7f3d89.jpg
A47: Alta Labs
A48: Altex
A49: Altronix
A50: Alvarado | B50: https://inishop.com/img/brand/thumb/27719_6ff56a1a04544fd9b05b104f68431a53.jpg
A51: Alvarion
A52: Amanco-Wavin
A53: Amazfit
A54: Amazon | B54: https://inishop.com/img/brand/thumb/5399_5dcad5ecf1114714be71e01331c69a40.jpg
A55: Amd | B55: https://inishop.com/img/brand/thumb/686_e2c5a136f8db4cf69e5e0e8cf2b2f417.jpg
A56: American Earth Anchors
A57: Ampad
A58: Amphenol
A59: Amprobe
A60: Anclo
A61: Andrew
A62: Andrew/Commscope
A63: Anviz
A64: Aoc | B64: https://images.icecat.biz/img/brand/thumb/1718_472c0e4c9d01478d872b6401f8d04669.jpg
A65: Apac Opto
A66: Apc | B66: https://images.icecat.biz/img/brand/thumb/33_68f38ab5dafc49faaa807fd70d2b6d33.jpg
A67: Aplicaciones Tecnologicas
A68: Apple | B68: https://inishop.com/img/brand/thumb/9_d14b59ec69c0456b8775a7210bbba1e9.jpg
A69: Apsa
A70: Arduino Llc
A71: Argomtech
A72: Arly
A73: Arrow
A74: Artesco
A75: Artline | B75: https://inishop.com/img/brand/thumb/303_620b0d5888b04ca5875626f57a56a07c.jpg
A76: Aruba
A77: Aspel
A78: Asrock | B78: https://inishop.com/img/brand/thumb/688_5bce5c6d5aa446b1a303b7a8312957f8.jpg
A79: Assa Abloy
A80: Astron
A81: Astronics Test Systems Inc
A82: Asus | B82: https://images.icecat.biz/img/brand/thumb/161_0457b539b0334f679d065c1176fa11ab.jpg
A83: ASUS | B83: https://images.icecat.biz/img/brand/thumb/161_0457b539b0334f679d065c1176fa11ab.jpg
A84: ASUS | B84: https://inishop.com/img/brand/thumb/85_2c884ebe400e4c88abdbe0f16f1d33f2.jpg
A85: ASUS | B85: https://images.icecat.biz/img/brand/thumb/739_aa2abbe6aded43bdabf4df493efecca8.jpg
A86: Asus Oem
A87: Aten | B87: https://images.icecat.biz/img/brand/thumb/2823_cbe873306b3c4c08b1ade01733975f88.jpg
A88: Atl
A89: Atlona
A90: Aufit
A91: Autodesk | B91: https://inishop.com/img/brand/thumb/172_65dfd9567f1643ba891b20f5265e563d.jpg
A92: Avcom
A93: Avery | B93: https://inishop.com/img/brand/thumb/6378_7431c0921f10482a9fee087ce89a0da8.jpg
A94: Axion
A95: Azor
A96: Backdrop
A97: Baco
A98: Badgy
A99: Balam Rush | B99: https://inishop.com/img/brand/thumb/41179_4192f762fe1949309d6a73f37e032b24.jpg
A100: Band It
...

Sheet Hoja3
A1: cmarca | C1: cimagen
A2: 3M | B2: =UPPER(A2) -> 3M | C2: https://images.icecat.biz/img/brand/thumb/206_d81d1d188e244538ab3082f8435acbd0.jpg
A3: Acer | B3: =UPPER(A3) -> ACER | C3: https://images.icecat.biz/img/brand/thumb/7_2e1091176d2d450eae2dce7506f1952f.jpg
A4: Adata | B4: =UPPER(A4) -> ADATA | C4: https://images.icecat.biz/img/brand/thumb/2634_2a848859d95b45c98590f1c44384958e.jpg
A5: Adata | B5: =UPPER(A5) -> ADATA | C5: https://images.icecat.biz/img/brand/thumb/32301_3243df0daeb740f998efd0a01bc129bb.jpg
A6: Aerocool | B6: =UPPER(A6) -> AEROCOOL | C6: https://images.icecat.biz/img/brand/thumb/1935_406c04e90f78451e8cdd4a6a2a4c0e6f.jpg
A7: Allied Telesis | B7: =UPPER(A7) -> ALLIED TELESIS | C7: https://images.icecat.biz/img/brand/thumb/49_8e89cb7fac62454a81797ce1e528cb76.jpg
A8: Aoc | B8: =UPPER(A8) -> AOC | C8: https://images.icecat.biz/img/brand/thumb/1718_472c0e4c9d01478d872b6401f8d04669.jpg
A9: Apc | B9: =UPPER(A9) -> APC | C9: https://images.icecat.biz/img/brand/thumb/33_68f38ab5dafc49faaa807fd70d2b6d33.jpg
A10: Asus | B10: =UPPER(A10) -> ASUS | C10: https://images.icecat.biz/img/brand/thumb/161_0457b539b0334f679d065c1176fa11ab.jpg
A11: ASUS | B11: =UPPER(A11) -> ASUS | C11: https://images.icecat.biz/img/brand/thumb/161_0457b539b0334f679d065c1176fa11ab.jpg
A12: ASUS | B12: =UPPER(A12) -> ASUS | C12: https://images.icecat.biz/img/brand/thumb/739_aa2abbe6aded43bdabf4df493efecca8.jpg
A13: Aten | B13: =UPPER(A13) -> ATEN | C13: https://images.icecat.biz/img/brand/thumb/2823_cbe873306b3c4c08b1ade01733975f88.jpg
... A95: Turtle Beach | B95: =UPPER(A95) -> TURTLE BEACH | C95: https://images.icecat.biz/img/brand/thumb/3256_5c751e86992a4aaba8abfc1c34493cf9.jpg
